[
  {
    "content_id": 297368,
    "reference_id": 109275,
    "title": "Jeremias 1.1–19",
    "media_type": "Text",
    "index_reference": "24001001-24001019",
    "language": "por",
    "content": "<p><span data-bnType=\"resourceReference\" data-resourceId=\"108507\" data-resourceType=\"BiblicaStudyNotesKeyTerms\">Jeremias</span> foi <span data-bnType=\"resourceReference\" data-resourceId=\"108358\" data-resourceType=\"BiblicaStudyNotesKeyTerms\">separado</span> por <span data-bnType=\"resourceReference\" data-resourceId=\"108199\" data-resourceType=\"BiblicaStudyNotesKeyTerms\">Deus</span> para ser um <span data-bnType=\"resourceReference\" data-resourceId=\"108416\" data-resourceType=\"BiblicaStudyNotesKeyTerms\">profeta</span>. Jeremias não achava que poderia fazer o <span data-bnType=\"resourceReference\" data-resourceId=\"108208\" data-resourceType=\"BiblicaStudyNotesKeyTerms\">trabalho</span> que Deus lhe designou. Suas dúvidas eram como as dúvidas que <span data-bnType=\"resourceReference\" data-resourceId=\"108300\" data-resourceType=\"BiblicaStudyNotesKeyTerms\">Moisés</span> teve centenas de anos antes (Êxodo capítulos 3 a 4). Deus disse a Moisés para falar com o rei do <span data-bnType=\"resourceReference\" data-resourceId=\"108251\" data-resourceType=\"BiblicaStudyNotesKeyTerms\">Egito</span>. Moisés disse a Deus que não conseguia falar bem. Deus disse a Jeremias para falar com nações e reinos. Ele deveria falar com os <span data-bnType=\"resourceReference\" data-resourceId=\"108330\" data-resourceType=\"BiblicaStudyNotesKeyTerms\">reis</span>, oficiais, <span data-bnType=\"resourceReference\" data-resourceId=\"108333\" data-resourceType=\"BiblicaStudyNotesKeyTerms\">sacerdotes</span> e ao povo do <span data-bnType=\"resourceReference\" data-resourceId=\"108480\" data-resourceType=\"BiblicaStudyNotesKeyTerms\">reino do sul</span>. Jeremias disse a Deus que não sabia como falar. Isso não era um problema para Deus. Deus deu a Jeremias as palavras para dizer. Deus avisou Jeremias que as pessoas com quem ele falasse lutariam contra ele. Isso significa que não o ouviriam e tentariam impedi-lo de falar. A <span data-bnType=\"resourceReference\" data-resourceId=\"108296\" data-resourceType=\"BiblicaStudyNotesKeyTerms\">visão</span> sobre o pote de água fervente explicou a principal mensagem de Deus. Era uma <span data-bnType=\"resourceReference\" data-resourceId=\"108534\" data-resourceType=\"BiblicaStudyNotesKeyTerms\">mensagem de julgamento</span> contra o reino do sul. Era um exemplo das mensagens de <span data-bnType=\"resourceReference\" data-resourceId=\"108233\" data-resourceType=\"BiblicaStudyNotesKeyTerms\">julgamento</span> que Jeremias compartilharia por muitos anos. Deus não queria que Jeremias tivesse medo das pessoas com quem falasse. Deus prometeu estar com Jeremias e salvá-lo.</p>",
    "associations": {
      "passage": [
        {
          "start_ref": "24001001",
          "start_ref_usfm": "JER 1:1",
          "end_ref": "24001019",
          "end_ref_usfm": "JER 1:19"
        }
      ],
      "resource": [
        {
          "reference_id": 108199,
          "content_id": 145708,
          "resource_code": "BiblicaStudyNotesKeyTerms",
          "label": "Deus",
          "language": "por"
        },
        {
          "reference_id": 108208,
          "content_id": 145717,
          "resource_code": "BiblicaStudyNotesKeyTerms",
          "label": "Trabalho",
          "language": "por"
        },
        {
          "reference_id": 108233,
          "content_id": 145742,
          "resource_code": "BiblicaStudyNotesKeyTerms",
          "label": "Julgamento",
          "language": "por"
        },
        {
          "reference_id": 108251,
          "content_id": 145760,
          "resource_code": "BiblicaStudyNotesKeyTerms",
          "label": "Egito",
          "language": "por"
        },
        {
          "reference_id": 108296,
          "content_id": 145805,
          "resource_code": "BiblicaStudyNotesKeyTerms",
          "label": "Visão",
          "language": "por"
        },
        {
          "reference_id": 108300,
          "content_id": 145809,
          "resource_code": "BiblicaStudyNotesKeyTerms",
          "label": "Moisés",
          "language": "por"
        },
        {
          "reference_id": 108330,
          "content_id": 145839,
          "resource_code": "BiblicaStudyNotesKeyTerms",
          "label": "Rei",
          "language": "por"
        },
        {
          "reference_id": 108333,
          "content_id": 145842,
          "resource_code": "BiblicaStudyNotesKeyTerms",
          "label": "Sacerdote",
          "language": "por"
        },
        {
          "reference_id": 108358,
          "content_id": 145867,
          "resource_code": "BiblicaStudyNotesKeyTerms",
          "label": "Separado",
          "language": "por"
        },
        {
          "reference_id": 108416,
          "content_id": 145925,
          "resource_code": "BiblicaStudyNotesKeyTerms",
          "label": "Profeta",
          "language": "por"
        },
        {
          "reference_id": 108480,
          "content_id": 145989,
          "resource_code": "BiblicaStudyNotesKeyTerms",
          "label": "Reino do Sul",
          "language": "por"
        },
        {
          "reference_id": 108507,
          "content_id": 146016,
          "resource_code": "BiblicaStudyNotesKeyTerms",
          "label": "Jeremias",
          "language": "por"
        },
        {
          "reference_id": 108534,
          "content_id": 146043,
          "resource_code": "BiblicaStudyNotesKeyTerms",
          "label": "Mensagens de julgamento",
          "language": "por"
        }
      ]
    }
  },
  {
    "content_id": 297369,
    "reference_id": 109276,
    "title": "Jeremias 2.1–12.17",
    "media_type": "Text",
    "index_reference": "24002001-24012017",
    "language": "por",
    "content": "<p>As mensagens de julgamento de Jeremias explicaram como e por que o <span data-bnType=\"resourceReference\" data-resourceId=\"108302\" data-resourceType=\"BiblicaStudyNotesKeyTerms\">povo de Deus</span> seria julgado. Essas mensagens eram como as mensagens de julgamento que <span data-bnType=\"resourceReference\" data-resourceId=\"108497\" data-resourceType=\"BiblicaStudyNotesKeyTerms\">Isaías</span> compartilhou. O trabalho de ser profeta foi muito difícil para Jeremias. Ele chorou e sofreu com profunda tristeza e dor. Dentro de seu próprio corpo, ele sentiu a <span data-bnType=\"resourceReference\" data-resourceId=\"108500\" data-resourceType=\"BiblicaStudyNotesKeyTerms\">ira de Deus</span> como um fogo ardente. O povo e os líderes do reino do sul não foram fiéis à <span data-bnType=\"resourceReference\" data-resourceId=\"108328\" data-resourceType=\"BiblicaStudyNotesKeyTerms\">aliança do Monte Sinai</span>. Eles não obedeceram aos <span data-bnType=\"resourceReference\" data-resourceId=\"108331\" data-resourceType=\"BiblicaStudyNotesKeyTerms\">Dez Mandamentos</span>. Eles não trataram os outros da maneira que Deus os ensinou na <span data-bnType=\"resourceReference\" data-resourceId=\"108335\" data-resourceType=\"BiblicaStudyNotesKeyTerms\">Lei de Moisés</span>. Eles trataram mal as <span data-bnType=\"resourceReference\" data-resourceId=\"108418\" data-resourceType=\"BiblicaStudyNotesKeyTerms\">pessoas necessitadas</span>. Eles adoraram <span data-bnType=\"resourceReference\" data-resourceId=\"108284\" data-resourceType=\"BiblicaStudyNotesKeyTerms\">falsos deuses</span> em vez de <span data-bnType=\"resourceReference\" data-resourceId=\"108332\" data-resourceType=\"BiblicaStudyNotesKeyTerms\">adorar somente a Deus</span>. Eles não sentiam <span data-bnType=\"resourceReference\" data-resourceId=\"108465\" data-resourceType=\"BiblicaStudyNotesKeyTerms\">vergonha</span> disso. Eles esperavam que Deus continuasse a abençoá-los. Isso mostrava que não apenas falavam mentiras, mas também viviam mentiras. Mostrava que não tinham bom senso ou <span data-bnType=\"resourceReference\" data-resourceId=\"108325\" data-resourceType=\"BiblicaStudyNotesKeyTerms\">sabedoria</span>. Eles não aprenderam com o exemplo do <span data-bnType=\"resourceReference\" data-resourceId=\"108479\" data-resourceType=\"BiblicaStudyNotesKeyTerms\">reino do norte</span>. Eles não aprenderam com as vezes no passado quando Deus trouxe julgamento contra eles. As cegonhas e outros pássaros tinham mais sabedoria do que o povo de Deus. O povo de Deus não o servia com todo o <span data-bnType=\"resourceReference\" data-resourceId=\"108419\" data-resourceType=\"BiblicaStudyNotesKeyTerms\">coração</span>. Deus descreveu isso como não sendo <span data-bnType=\"resourceReference\" data-resourceId=\"108257\" data-resourceType=\"BiblicaStudyNotesKeyTerms\">circuncidados</span> em seus corações. Seus corpos eram circuncidados. Então, do lado de fora de seus corpos, eles tinham o sinal da <span data-bnType=\"resourceReference\" data-resourceId=\"108237\" data-resourceType=\"BiblicaStudyNotesKeyTerms\">aliança</span> de Deus. Mas as escolhas que faziam mostravam que não respeitavam e honravam a Deus. Isso era verdade tanto para o povo quanto para os líderes do reino do sul. Os reis, sacerdotes e profetas não seguiam o exemplo de Deus para <span data-bnType=\"resourceReference\" data-resourceId=\"108209\" data-resourceType=\"BiblicaStudyNotesKeyTerms\">governantes</span>. Eles não conheciam as leis de Deus e não lideravam o povo em obedecer a Deus. Eles mentiam dizendo que tudo estava indo bem e que a nação tinha <span data-bnType=\"resourceReference\" data-resourceId=\"108211\" data-resourceType=\"BiblicaStudyNotesKeyTerms\">paz</span>. Como resultado disso, Deus não impediria mais que as <span data-bnType=\"resourceReference\" data-resourceId=\"108380\" data-resourceType=\"BiblicaStudyNotesKeyTerms\">maldições da aliança</span> viessem. Deus ansiava por <span data-bnType=\"resourceReference\" data-resourceId=\"108281\" data-resourceType=\"BiblicaStudyNotesKeyTerms\">perdoar</span> seu povo. Ele queria que eles se afastassem do <span data-bnType=\"resourceReference\" data-resourceId=\"108195\" data-resourceType=\"BiblicaStudyNotesKeyTerms\">pecado</span>, <span data-bnType=\"resourceReference\" data-resourceId=\"108346\" data-resourceType=\"BiblicaStudyNotesKeyTerms\">se arrependessem</span> e o seguissem. Mas eles recusaram. Então Deus disse a Jeremias para parar de <span data-bnType=\"resourceReference\" data-resourceId=\"108227\" data-resourceType=\"BiblicaStudyNotesKeyTerms\">orar</span> para que Deus tivesse <span data-bnType=\"resourceReference\" data-resourceId=\"108342\" data-resourceType=\"BiblicaStudyNotesKeyTerms\">misericórdia</span> deles. Deus usaria o exército <span data-bnType=\"resourceReference\" data-resourceId=\"108498\" data-resourceType=\"BiblicaStudyNotesKeyTerms\">babilônico</span> como <span data-bnType=\"resourceReference\" data-resourceId=\"108415\" data-resourceType=\"BiblicaStudyNotesKeyTerms\">seu instrumento</span> para julgar o reino do sul. O <span data-bnType=\"resourceReference\" data-resourceId=\"108417\" data-resourceType=\"BiblicaStudyNotesKeyTerms\">Templo</span> seria destruído. O povo seria expulso da terra que Deus lhes havia dado. Deus havia avisado <span data-bnType=\"resourceReference\" data-resourceId=\"108473\" data-resourceType=\"BiblicaStudyNotesKeyTerms\">Salomão</span> sobre esse julgamento (1 Reis 9.6–9). No entanto, Deus prometeu que não destruiria completamente seu povo. Ele sempre permitiria que alguns permanecessem vivos. Dessa forma, Deus permaneceria fiel à sua <span data-bnType=\"resourceReference\" data-resourceId=\"108466\" data-resourceType=\"BiblicaStudyNotesKeyTerms\">aliança com Davi</span>. Deus também deu a Jeremias mensagens de esperança para compartilhar sobre um tempo futuro. Deus viveria com seu povo e governaria o <span data-bnType=\"resourceReference\" data-resourceId=\"108215\" data-resourceType=\"BiblicaStudyNotesKeyTerms\">mundo</span> de <span data-bnType=\"resourceReference\" data-resourceId=\"108464\" data-resourceType=\"BiblicaStudyNotesKeyTerms\">Jerusalém</span> como Rei. Os reinos do norte e do sul viveriam juntos em sua terra como um só reino novamente. Deus devolveria todas as nações às suas próprias terras. Os <span data-bnType=\"resourceReference\" data-resourceId=\"108503\" data-resourceType=\"BiblicaStudyNotesKeyTerms\">judeus</span> ensinariam outras nações que Deus é o <span data-bnType=\"resourceReference\" data-resourceId=\"108226\" data-resourceType=\"BiblicaStudyNotesKeyTerms\">Senhor</span> que governa sobre todos. Cada nação seria convidada a seguir as práticas que Deus ensinou ao seu povo. Cada grupo de pessoas que honrasse a Deus se tornaria parte do povo de Deus.</p>",
    "associations": {
      "passage": [
        {
          "start_ref": "24002001",
          "start_ref_usfm": "JER 2:1",
          "end_ref": "24012017",
          "end_ref_usfm": "JER 12:17"
        }
      ],
      "resource": [
        {
          "reference_id": 108195,
          "content_id": 145704,
          "resource_code": "BiblicaStudyNotesKeyTerms",
          "label": "Pecado",
          "language": "por"
        },
        {
          "reference_id": 108209,
          "content_id": 145718,
          "resource_code": "BiblicaStudyNotesKeyTerms",
          "label": "Governantes",
          "language": "por"
        },
        {
          "reference_id": 108211,
          "content_id": 145720,
          "resource_code": "BiblicaStudyNotesKeyTerms",
          "label": "Paz",
          "language": "por"
        },
        {
          "reference_id": 108215,
          "content_id": 145724,
          "resource_code": "BiblicaStudyNotesKeyTerms",
          "label": "Mundo",
          "language": "por"
        },
        {
          "reference_id": 108226,
          "content_id": 145735,
          "resource_code": "BiblicaStudyNotesKeyTerms",
          "label": "Senhor",
          "language": "por"
        },
        {
          "reference_id": 108227,
          "content_id": 145736,
          "resource_code": "BiblicaStudyNotesKeyTerms",
          "label": "Oração",
          "language": "por"
        },
        {
          "reference_id": 108237,
          "content_id": 145746,
          "resource_code": "BiblicaStudyNotesKeyTerms",
          "label": "Aliança",
          "language": "por"
        },
        {
          "reference_id": 108257,
          "content_id": 145766,
          "resource_code": "BiblicaStudyNotesKeyTerms",
          "label": "Circuncisão",
          "language": "por"
        },
        {
          "reference_id": 108281,
          "content_id": 145790,
          "resource_code": "BiblicaStudyNotesKeyTerms",
          "label": "Perdoar",
          "language": "por"
        },
        {
          "reference_id": 108284,
          "content_id": 145793,
          "resource_code": "BiblicaStudyNotesKeyTerms",
          "label": "Falsos deuses",
          "language": "por"
        },
        {
          "reference_id": 108302,
          "content_id": 145811,
          "resource_code": "BiblicaStudyNotesKeyTerms",
          "label": "O povo de Deus",
          "language": "por"
        },
        {
          "reference_id": 108325,
          "content_id": 145834,
          "resource_code": "BiblicaStudyNotesKeyTerms",
          "label": "Sabedoria",
          "language": "por"
        },
        {
          "reference_id": 108328,
          "content_id": 145837,
          "resource_code": "BiblicaStudyNotesKeyTerms",
          "label": "Aliança do Monte Sinai",
          "language": "por"
        },
        {
          "reference_id": 108331,
          "content_id": 145840,
          "resource_code": "BiblicaStudyNotesKeyTerms",
          "label": "Dez Mandamentos",
          "language": "por"
        },
        {
          "reference_id": 108332,
          "content_id": 145841,
          "resource_code": "BiblicaStudyNotesKeyTerms",
          "label": "Adore apenas Deus",
          "language": "por"
        },
        {
          "reference_id": 108335,
          "content_id": 145844,
          "resource_code": "BiblicaStudyNotesKeyTerms",
          "label": "Lei de Moisés",
          "language": "por"
        },
        {
          "reference_id": 108342,
          "content_id": 145851,
          "resource_code": "BiblicaStudyNotesKeyTerms",
          "label": "Misericórdia",
          "language": "por"
        },
        {
          "reference_id": 108346,
          "content_id": 145855,
          "resource_code": "BiblicaStudyNotesKeyTerms",
          "label": "Arrepender-se",
          "language": "por"
        },
        {
          "reference_id": 108380,
          "content_id": 145889,
          "resource_code": "BiblicaStudyNotesKeyTerms",
          "label": "Maldições da aliança",
          "language": "por"
        },
        {
          "reference_id": 108415,
          "content_id": 145924,
          "resource_code": "BiblicaStudyNotesKeyTerms",
          "label": "Ferramenta de Deus",
          "language": "por"
        },
        {
          "reference_id": 108417,
          "content_id": 145926,
          "resource_code": "BiblicaStudyNotesKeyTerms",
          "label": "Templo",
          "language": "por"
        },
        {
          "reference_id": 108418,
          "content_id": 145927,
          "resource_code": "BiblicaStudyNotesKeyTerms",
          "label": "Pessoas necessitadas",
          "language": "por"
        },
        {
          "reference_id": 108419,
          "content_id": 145928,
          "resource_code": "BiblicaStudyNotesKeyTerms",
          "label": "Coração",
          "language": "por"
        },
        {
          "reference_id": 108464,
          "content_id": 145973,
          "resource_code": "BiblicaStudyNotesKeyTerms",
          "label": "Jerusalém",
          "language": "por"
        },
        {
          "reference_id": 108465,
          "content_id": 145974,
          "resource_code": "BiblicaStudyNotesKeyTerms",
          "label": "Vergonha e honra",
          "language": "por"
        },
        {
          "reference_id": 108466,
          "content_id": 145975,
          "resource_code": "BiblicaStudyNotesKeyTerms",
          "label": "Aliança com Davi",
          "language": "por"
        },
        {
          "reference_id": 108473,
          "content_id": 145982,
          "resource_code": "BiblicaStudyNotesKeyTerms",
          "label": "Salomão",
          "language": "por"
        },
        {
          "reference_id": 108479,
          "content_id": 145988,
          "resource_code": "BiblicaStudyNotesKeyTerms",
          "label": "Reino do Norte",
          "language": "por"
        },
        {
          "reference_id": 108497,
          "content_id": 146006,
          "resource_code": "BiblicaStudyNotesKeyTerms",
          "label": "Isaías",
          "language": "por"
        },
        {
          "reference_id": 108498,
          "content_id": 146007,
          "resource_code": "BiblicaStudyNotesKeyTerms",
          "label": "Babilônia",
          "language": "por"
        },
        {
          "reference_id": 108500,
          "content_id": 146009,
          "resource_code": "BiblicaStudyNotesKeyTerms",
          "label": "Ira de Deus",
          "language": "por"
        },
        {
          "reference_id": 108503,
          "content_id": 146012,
          "resource_code": "BiblicaStudyNotesKeyTerms",
          "label": "Judeu",
          "language": "por"
        }
      ]
    }
  },
  {
    "content_id": 297370,
    "reference_id": 109277,
    "title": "Jeremias 13.1–24.10",
    "media_type": "Text",
    "index_reference": "24013001-24024010",
    "language": "por",
    "content": "<p>Jeremias compartilhou mensagens de julgamento de Deus repetidamente de várias maneiras. Algumas ele compartilhou através de uma <span data-bnType=\"resourceReference\" data-resourceId=\"108537\" data-resourceType=\"BiblicaStudyNotesKeyTerms\">ação de profecia</span>. Este foi o caso com o cinto de linho e o jarro de barro do oleiro. Também foi o caso de como Jeremias não deveria se <span data-bnType=\"resourceReference\" data-resourceId=\"108206\" data-resourceType=\"BiblicaStudyNotesKeyTerms\">casar</span> ou ter filhos. Outras mensagens Jeremias falou como <span data-bnType=\"resourceReference\" data-resourceId=\"108204\" data-resourceType=\"BiblicaStudyNotesKeyTerms\">poemas</span> ou simplesmente ao conversar com alguém. Este foi o caso quando ele falou com Pasur e os oficiais enviados por Zedequias.Em suas mensagens Deus comparou seu povo a muitas coisas diferentes. Isso deu ao seu povo imagens para ajudá-los a entender o que ele queria dizer. Ele os comparou a odres, barro sendo moldado por um oleiro e cestos de figos. Ele os comparou a uma <span data-bnType=\"resourceReference\" data-resourceId=\"108535\" data-resourceType=\"BiblicaStudyNotesKeyTerms\">prostituta</span> e a uma esposa que não era fiel ao seu marido. Nessa imagem, Deus era o marido. O povo e os líderes do reino do sul eram a esposa. Adorar falsos deuses era como eles eram infiéis a ele. Deus comparou os líderes a <span data-bnType=\"resourceReference\" data-resourceId=\"108278\" data-resourceType=\"BiblicaStudyNotesKeyTerms\">pastores</span>. Nessa imagem, o povo era as ovelhas de Deus. Os reis, sacerdotes e profetas eram pastores que os destruíam e dispersavam. Às vezes, Deus enviava suas mensagens com um sinal. Este foi o caso quando Deus não deixou chover por um tempo. <span data-bnType=\"resourceReference\" data-resourceId=\"108550\" data-resourceType=\"BiblicaStudyNotesKeyTerms\">Falsos profetas</span> compartilhavam mensagens que não eram de Deus. Suas mensagens eram mentiras sobre paz e bons tempos. Isso deixou Deus muito zangado. Jeremias compartilhou as mensagens de Deus fielmente. Deus havia avisado Jeremias que o povo e os líderes lutariam contra ele. Isso aconteceu muitas vezes. As pessoas se recusaram a ouvir Jeremias e zombaram dele. Fizeram planos malignos contra ele, bateram nele e o colocaram na prisão. Deus havia prometido estar com Jeremias. Deus havia prometido salvá-lo daqueles que o tratavam mal. Mas Jeremias estava sofrendo terrivelmente. Ele sentiu que Deus o havia enganado quando prometeu estar com ele. No entanto, Jeremias permaneceu fiel a Deus enquanto sofria. Dessa forma, ele era como <span data-bnType=\"resourceReference\" data-resourceId=\"108524\" data-resourceType=\"BiblicaStudyNotesKeyTerms\">Jó</span>. Jeremias foi honesto com Deus quando orou. Suas orações eram como os poemas e cânticos no livro de Salmos. Incluíam clamores por ajuda e reclamações. Jeremias também louvou a Deus e falou sobre como confiava em Deus. A mensagem de esperança no capítulo 23 falava sobre um rei da <span data-bnType=\"resourceReference\" data-resourceId=\"108220\" data-resourceType=\"BiblicaStudyNotesKeyTerms\">linhagem</span> de <span data-bnType=\"resourceReference\" data-resourceId=\"108449\" data-resourceType=\"BiblicaStudyNotesKeyTerms\">Davi</span>. Ele não seria como os reis gananciosos do reino do sul. Ele seguiria as regras de Deus para reis registradas em Deuteronômio 17.14–20. Este rei foi chamado de Ramo piedoso. Isaías também havia profetizado sobre este Ramo (Isaías 11.1–3). Os judeus passaram a entender esta mensagem de esperança como uma <span data-bnType=\"resourceReference\" data-resourceId=\"108399\" data-resourceType=\"BiblicaStudyNotesKeyTerms\">profecia</span> sobre o <span data-bnType=\"resourceReference\" data-resourceId=\"108527\" data-resourceType=\"BiblicaStudyNotesKeyTerms\">Messias</span>. Os escritores do <span data-bnType=\"resourceReference\" data-resourceId=\"108528\" data-resourceType=\"BiblicaStudyNotesKeyTerms\">Novo Testamento</span> passaram a entendê-la como uma <span data-bnType=\"resourceReference\" data-resourceId=\"108400\" data-resourceType=\"BiblicaStudyNotesKeyTerms\">profecia sobre Jesus</span>. <span data-bnType=\"resourceReference\" data-resourceId=\"108219\" data-resourceType=\"BiblicaStudyNotesKeyTerms\">Jesus</span> é o Ramo que torna as pessoas <span data-bnType=\"resourceReference\" data-resourceId=\"108254\" data-resourceType=\"BiblicaStudyNotesKeyTerms\">justas diante de Deus</span>.</p>",
    "associations": {
      "passage": [
        {
          "start_ref": "24013001",
          "start_ref_usfm": "JER 13:1",
          "end_ref": "24024010",
          "end_ref_usfm": "JER 24:10"
        }
      ],
      "resource": [
        {
          "reference_id": 108204,
          "content_id": 145713,
          "resource_code": "BiblicaStudyNotesKeyTerms",
          "label": "Poema",
          "language": "por"
        },
        {
          "reference_id": 108206,
          "content_id": 145715,
          "resource_code": "BiblicaStudyNotesKeyTerms",
          "label": "Casamento",
          "language": "por"
        },
        {
          "reference_id": 108219,
          "content_id": 145728,
          "resource_code": "BiblicaStudyNotesKeyTerms",
          "label": "Jesus",
          "language": "por"
        },
        {
          "reference_id": 108220,
          "content_id": 145729,
          "resource_code": "BiblicaStudyNotesKeyTerms",
          "label": "Linhagem familiar",
          "language": "por"
        },
        {
          "reference_id": 108254,
          "content_id": 145763,
          "resource_code": "BiblicaStudyNotesKeyTerms",
          "label": "Certo com Deus",
          "language": "por"
        },
        {
          "reference_id": 108278,
          "content_id": 145787,
          "resource_code": "BiblicaStudyNotesKeyTerms",
          "label": "Pastor",
          "language": "por"
        },
        {
          "reference_id": 108399,
          "content_id": 145908,
          "resource_code": "BiblicaStudyNotesKeyTerms",
          "label": "Profecia",
          "language": "por"
        },
        {
          "reference_id": 108400,
          "content_id": 145909,
          "resource_code": "BiblicaStudyNotesKeyTerms",
          "label": "Profecias sobre Jesus",
          "language": "por"
        },
        {
          "reference_id": 108449,
          "content_id": 145958,
          "resource_code": "BiblicaStudyNotesKeyTerms",
          "label": "Davi",
          "language": "por"
        },
        {
          "reference_id": 108524,
          "content_id": 146033,
          "resource_code": "BiblicaStudyNotesKeyTerms",
          "label": "Jó",
          "language": "por"
        },
        {
          "reference_id": 108527,
          "content_id": 146036,
          "resource_code": "BiblicaStudyNotesKeyTerms",
          "label": "Messias",
          "language": "por"
        },
        {
          "reference_id": 108528,
          "content_id": 146037,
          "resource_code": "BiblicaStudyNotesKeyTerms",
          "label": "Novo Testamento",
          "language": "por"
        },
        {
          "reference_id": 108535,
          "content_id": 146044,
          "resource_code": "BiblicaStudyNotesKeyTerms",
          "label": "Prostituto",
          "language": "por"
        },
        {
          "reference_id": 108537,
          "content_id": 146046,
          "resource_code": "BiblicaStudyNotesKeyTerms",
          "label": "Ações de profecia",
          "language": "por"
        },
        {
          "reference_id": 108550,
          "content_id": 146059,
          "resource_code": "BiblicaStudyNotesKeyTerms",
          "label": "Falso profeta",
          "language": "por"
        }
      ]
    }
  },
  {
    "content_id": 297371,
    "reference_id": 109278,
    "title": "Jeremias 25.1–38",
    "media_type": "Text",
    "index_reference": "24025001-24025038",
    "language": "por",
    "content": "<p>Jeremias explicou que Babilônia governaria sobre muitas nações. Ele explicou isso durante o quarto ano de Jeoaquim como rei do reino do sul. Isso foi no ano <span data-bnType=\"resourceReference\" data-resourceId=\"108551\" data-resourceType=\"BiblicaStudyNotesKeyTerms\">605 a.C.</span>. As nações teriam que servir a Babilônia por <span data-bnType=\"resourceReference\" data-resourceId=\"108552\" data-resourceType=\"BiblicaStudyNotesKeyTerms\">70 anos</span>. Esta mensagem de julgamento foi explicada através de um sinal. O sinal era um copo. O vinho dentro do copo foi descrito como a ira de Deus. Os líderes do reino do sul deveriam beber do copo. Assim como os líderes das nações ao redor do reino do sul. Eles não podiam escolher não beber. Era obrigatório. Isso mostrava que Deus traria julgamento contra eles. As mensagens de Jeremias registradas nos capítulos 46 a 51 explicam o julgamento contra essas nações. Deus usaria <span data-bnType=\"resourceReference\" data-resourceId=\"108501\" data-resourceType=\"BiblicaStudyNotesKeyTerms\">Nabucodonosor</span> como sua ferramenta para trazer julgamento.</p>",
    "associations": {
      "passage": [
        {
          "start_ref": "24025001",
          "start_ref_usfm": "JER 25:1",
          "end_ref": "24025038",
          "end_ref_usfm": "JER 25:38"
        }
      ],
      "resource": [
        {
          "reference_id": 108501,
          "content_id": 146010,
          "resource_code": "BiblicaStudyNotesKeyTerms",
          "label": "Nabucodonosor",
          "language": "por"
        },
        {
          "reference_id": 108551,
          "content_id": 146060,
          "resource_code": "BiblicaStudyNotesKeyTerms",
          "label": "605 a.C.",
          "language": "por"
        },
        {
          "reference_id": 108552,
          "content_id": 146061,
          "resource_code": "BiblicaStudyNotesKeyTerms",
          "label": "70 anos",
          "language": "por"
        }
      ]
    }
  },
  {
    "content_id": 297372,
    "reference_id": 109279,
    "title": "Jeremias 26.1–29.32",
    "media_type": "Text",
    "index_reference": "24026001-24029032",
    "language": "por",
    "content": "<p>Enquanto Jeoaquim era rei, um grupo de sacerdotes, profetas e oficiais quase matou Jeremias. Enquanto Zedequias era rei, Hananias tentou provar que Jeremias estava mentindo. Hananias era um falso profeta. Ele falou uma mensagem que ia contra as mensagens de Jeremias. Semaías também era um falso profeta. Ele vivia no <span data-bnType=\"resourceReference\" data-resourceId=\"108495\" data-resourceType=\"BiblicaStudyNotesKeyTerms\">exílio</span> em Babilônia. Ele contou aos judeus na Babilônia mensagens que iam contra as mensagens de Jeremias. Esses exemplos mostram algo sobre o povo e os líderes do reino do sul. Eles se opuseram fortemente a Jeremias e suas mensagens. Eles fizeram isso antes e depois de o governo babilônico tomar controle do reino do sul. A carta de Jeremias era para pessoas do reino do sul vivendo na Babilônia. Eles foram o primeiro grupo de judeus que Nabucodonosor forçou a deixar <span data-bnType=\"resourceReference\" data-resourceId=\"108291\" data-resourceType=\"BiblicaStudyNotesKeyTerms\">Judá</span>. Jeremias explicou como Deus queria que os judeus vivessem durante o exílio. Deus queria que eles aceitassem que o exílio era o julgamento que ele havia prometido trazer. Ele queria que eles aceitassem quanto tempo duraria. Eles mostrariam que aceitavam essas coisas fazendo da Babilônia seu lar. Eles fariam dela seu lar construindo casas, formando famílias e plantando jardins. Eles fariam dela seu lar trabalhando arduamente lá e orando pela cidade. Deus planejou que eles tivessem sucesso na Babilônia. Eles não precisavam temer que Deus lhes causasse mal enquanto estivessem lá. Ele queria que eles tivessem esperança durante seu tempo no exílio. Seu povo o encontraria quando o buscassem de todo o coração. Isso era verdade mesmo estando longe de Jerusalém e do Templo. Salomão havia orado sobre isso quando o templo foi consagrado a Deus (1 Reis 8.46–51). Deus também queria que seu povo tivesse esperança para quando o exílio terminasse. Ele queria que confiassem que os traria de volta a Judá. Deus faria isso após 70 anos. Mas os judeus na Babilônia não queriam aceitar essas coisas. Eles queriam fingir que estariam de volta a Judá muito em breve. Eles queriam fingir que a vida em Judá seria melhor do que a vida na Babilônia. Isso era uma forma de fingir que Deus não estava trazendo julgamento contra seu povo. Era uma forma de fingir que não haviam pecado contra Deus. Isso significava que os judeus na Babilônia não tinham ouvido.</p>",
    "associations": {
      "passage": [
        {
          "start_ref": "24026001",
          "start_ref_usfm": "JER 26:1",
          "end_ref": "24029032",
          "end_ref_usfm": "JER 29:32"
        }
      ],
      "resource": [
        {
          "reference_id": 108291,
          "content_id": 145800,
          "resource_code": "BiblicaStudyNotesKeyTerms",
          "label": "Judá",
          "language": "por"
        },
        {
          "reference_id": 108495,
          "content_id": 146004,
          "resource_code": "BiblicaStudyNotesKeyTerms",
          "label": "Exílio",
          "language": "por"
        }
      ]
    }
  },
  {
    "content_id": 297373,
    "reference_id": 109280,
    "title": "Jeremias 30.1–33.26",
    "media_type": "Text",
    "index_reference": "24030001-24033026",
    "language": "por",
    "content": "<p>As mensagens de esperança nestes capítulos são sobre Deus abençoando seu povo. Isso aconteceria após o tempo de julgamento terminar. A linhagem familiar de <span data-bnType=\"resourceReference\" data-resourceId=\"108268\" data-resourceType=\"BiblicaStudyNotesKeyTerms\">Jacó</span> seria trazida de volta à sua terra. Eles viveriam fiéis a Deus como seu povo. Ele seria o único Deus que adorariam e serviriam. Isso lhes permitiria desfrutar das <span data-bnType=\"resourceReference\" data-resourceId=\"108379\" data-resourceType=\"BiblicaStudyNotesKeyTerms\">bênçãos da aliança</span>. Deus lhes daria paz, <span data-bnType=\"resourceReference\" data-resourceId=\"108212\" data-resourceType=\"BiblicaStudyNotesKeyTerms\">descanso</span>, segurança e proteção. Deus os curaria e lhes daria saúde e sucesso. Ele compartilharia livremente com eles seu amor terno e fiel. Seu rei seria o Ramo da linhagem familiar de Davi. Este rei faria o que era justo e correto. O povo adoraria a Deus das maneiras que ele lhes ensinou. Os sacerdotes e <span data-bnType=\"resourceReference\" data-resourceId=\"108343\" data-resourceType=\"BiblicaStudyNotesKeyTerms\">levitas</span> garantiriam isso. Deus havia descrito como o pecado de seu povo estava gravado na tábua de seus corações. Ele havia dito isso em uma mensagem de julgamento registrada em Jeremias 17.1. Nessas mensagens de esperança, ele disse que algo diferente seria escrito em seus corações. Deus prometeu escrever sua lei em seus corações. Esta era a forma de Deus fazer uma <span data-bnType=\"resourceReference\" data-resourceId=\"108553\" data-resourceType=\"BiblicaStudyNotesKeyTerms\">nova aliança</span> com seu povo. A lei da aliança do <span data-bnType=\"resourceReference\" data-resourceId=\"108327\" data-resourceType=\"BiblicaStudyNotesKeyTerms\">Monte Sinai</span> havia sido escrita em <span data-bnType=\"resourceReference\" data-resourceId=\"108339\" data-resourceType=\"BiblicaStudyNotesKeyTerms\">tábuas de pedra</span>. Ter a lei de Deus escrita em seus corações era uma maneira de descrever algo. Significava que o povo de Deus realmente conheceria quem Deus é. Conhecer a Deus os tornaria capazes de entender claramente o que era o pecado e o mal. Então, eles fariam a escolha de dizer não ao mal e sim a Deus. Eles adorariam, serviriam e obedeceriam a ele. Isso é o que Deus sempre quis para os <span data-bnType=\"resourceReference\" data-resourceId=\"108202\" data-resourceType=\"BiblicaStudyNotesKeyTerms\">seres humanos</span>. O pecado e o mal continuariam sendo um problema para o povo de Deus. Mas eles confiariam em Deus para cuidar desse problema. Deus cuidaria disso perdoando seus pecados e seus caminhos maus. Ao contrário das mensagens de julgamento, essas mensagens de esperança eram agradáveis para Jeremias. Ele comprou um pedaço de terra como um sinal. Era um sinal de que o povo de Deus compraria e venderia terras novamente no futuro. Era um sinal de que as promessas de Deus nas mensagens de esperança se tornariam realidade. Os judeus reconheceram que algumas das promessas se realizaram após o exílio. Eles passaram a entender que algumas das promessas se realizariam no futuro. Isso aconteceria quando o Messias viesse. Os escritores do Novo Testamento mostraram que Jesus colocou a nova aliança em vigor. Jesus tornou possível que as pessoas fossem libertadas do poder do pecado e do mal.</p>",
    "associations": {
      "passage": [
        {
          "start_ref": "24030001",
          "start_ref_usfm": "JER 30:1",
          "end_ref": "24033026",
          "end_ref_usfm": "JER 33:26"
        }
      ],
      "resource": [
        {
          "reference_id": 108202,
          "content_id": 145711,
          "resource_code": "BiblicaStudyNotesKeyTerms",
          "label": "Seres humanos",
          "language": "por"
        },
        {
          "reference_id": 108212,
          "content_id": 145721,
          "resource_code": "BiblicaStudyNotesKeyTerms",
          "label": "Descanso",
          "language": "por"
        },
        {
          "reference_id": 108268,
          "content_id": 145777,
          "resource_code": "BiblicaStudyNotesKeyTerms",
          "label": "Jacó",
          "language": "por"
        },
        {
          "reference_id": 108327,
          "content_id": 145836,
          "resource_code": "BiblicaStudyNotesKeyTerms",
          "label": "Monte Sinai",
          "language": "por"
        },
        {
          "reference_id": 108339,
          "content_id": 145848,
          "resource_code": "BiblicaStudyNotesKeyTerms",
          "label": "Tábuas de pedra",
          "language": "por"
        },
        {
          "reference_id": 108343,
          "content_id": 145852,
          "resource_code": "BiblicaStudyNotesKeyTerms",
          "label": "Levitas",
          "language": "por"
        },
        {
          "reference_id": 108379,
          "content_id": 145888,
          "resource_code": "BiblicaStudyNotesKeyTerms",
          "label": "Bênçãos da aliança",
          "language": "por"
        },
        {
          "reference_id": 108553,
          "content_id": 146062,
          "resource_code": "BiblicaStudyNotesKeyTerms",
          "label": "Nova aliança",
          "language": "por"
        }
      ]
    }
  },
  {
    "content_id": 297374,
    "reference_id": 109281,
    "title": "Jeremias 34.1–45.5",
    "media_type": "Text",
    "index_reference": "24034001-24045005",
    "language": "por",
    "content": "<p>Esses capítulos são uma coleção de histórias da vida de Jeremias. Eles incluem eventos desde o governo de Jeoaquim até o tempo após a destruição de Jerusalém. Essas histórias mostram algo sobre o povo e os líderes do reino do sul. Eles não prestaram atenção ao que o Senhor havia dito por meio de Jeremias. Isso aconteceu antes e depois de o governo babilônico tomar o controle do reino do sul. A história sobre a linhagem da família de Recabe deu um exemplo de obediência fiel. A linhagem da família de Recabe obedeceu fielmente às instruções do filho de Recabe, Jonadabe. Deus usou a capacidade deles de obedecer como exemplo. Comparado à família de Recabe, ficou claro que o povo de Deus se recusava a obedecê-lo. Outro exemplo disso foi o que o rei Jeoaquim fez após ouvir as mensagens de Deus. Baruque era um secretário. Ele escreveu em rolos as mensagens que Jeremias havia falado por muitos anos. Jeoaquim queimou os rolos e tentou prender Jeremias e Baruque. Baruque os escreveu novamente com ainda mais mensagens. Mais tarde, outros oficiais prenderam Jeremias. Alguns tentaram matá-lo para que ele parasse de falar as mensagens de Deus. O rei Zedequias pediu conselhos a Jeremias. Ele pediu a Jeremias que orasse por ele. Jeremias deu-lhe instruções sobre ser humilde e servir ao rei da Babilônia. Mas Zedequias e seus oficiais não seguiram essas instruções. Nem obedeceram às instruções na Lei de Moisés sobre <span data-bnType=\"resourceReference\" data-resourceId=\"108258\" data-resourceType=\"BiblicaStudyNotesKeyTerms\">escravos</span> e <span data-bnType=\"resourceReference\" data-resourceId=\"108378\" data-resourceType=\"BiblicaStudyNotesKeyTerms\">servos</span>. Eles haviam prometido libertar seus escravos, mas depois mudaram de ideia. Por causa dessas coisas, Deus permitiu que Nabucodonosor destruísse completamente Jerusalém. Os babilônios trataram bem Jeremias e o libertaram. Gedalias era um líder que prestava atenção às mensagens de Deus. Ele entendia que o reino do sul deveria servir à Babilônia. Como governador de Judá, foi isso que ele levou o povo a fazer. Mas um oficial da linhagem da família de Davi matou Gedalias. Então, um grande grupo dos que restaram no reino do sul fugiu para o Egito. Eles achavam que estariam seguros das tropas da Babilônia lá. Jeremias os advertiu para não fazerem isso. Mas esse grupo forçou Jeremias e Baruque a irem com eles para o Egito. No Egito, esse grupo de judeus adorou um falso deus chamado Rainha do Céu. Eles acreditavam que Jerusalém havia sido destruída porque, por um tempo, haviam parado de adorá-la. Isso mostrou que eles não ouviram Jeremias nem entenderam as mensagens de Deus. Deus havia prometido que Baruque não seria morto quando o problema chegasse a Jerusalém. Não se sabe o que aconteceu com Jeremias e Baruque no Egito.</p>",
    "associations": {
      "passage": [
        {
          "start_ref": "24034001",
          "start_ref_usfm": "JER 34:1",
          "end_ref": "24045005",
          "end_ref_usfm": "JER 45:5"
        }
      ],
      "resource": [
        {
          "reference_id": 108258,
          "content_id": 145767,
          "resource_code": "BiblicaStudyNotesKeyTerms",
          "label": "Escravos",
          "language": "por"
        },
        {
          "reference_id": 108378,
          "content_id": 145887,
          "resource_code": "BiblicaStudyNotesKeyTerms",
          "label": "Servos",
          "language": "por"
        }
      ]
    }
  },
  {
    "content_id": 297375,
    "reference_id": 109282,
    "title": "Jeremias 46.1–49.39",
    "media_type": "Text",
    "index_reference": "24046001-24049039",
    "language": "por",
    "content": "<p>As mensagens de julgamento nestes capítulos são sobre as nações ao redor do reino do sul. No capítulo 25, Jeremias havia anunciado que Deus traria julgamento contra elas. Essas mensagens explicam esse julgamento. O ponto principal das mensagens é que essas nações seriam destruídas pela Babilônia. Deus traria seu julgamento contra o Egito, os <span data-bnType=\"resourceReference\" data-resourceId=\"108267\" data-resourceType=\"BiblicaStudyNotesKeyTerms\">filisteus</span>, <span data-bnType=\"resourceReference\" data-resourceId=\"108397\" data-resourceType=\"BiblicaStudyNotesKeyTerms\">Moabe</span>, <span data-bnType=\"resourceReference\" data-resourceId=\"108412\" data-resourceType=\"BiblicaStudyNotesKeyTerms\">Amom</span> e <span data-bnType=\"resourceReference\" data-resourceId=\"108411\" data-resourceType=\"BiblicaStudyNotesKeyTerms\">Edom</span>. Ele o traria contra <span data-bnType=\"resourceReference\" data-resourceId=\"108540\" data-resourceType=\"BiblicaStudyNotesKeyTerms\">Damasco</span>, Quedar, Hazor e Elão. Deus os julgou por serem orgulhosos, tratarem os outros mal e confiarem em falsos deuses. Deus se importava profundamente com essas nações e com o que acontecia com elas. Ele se deleitava em Damasco. Ele chorou por Moabe. Ele prometeu estabelecer seu trono em Elão. Deus queria que essas nações soubessem que ele é o Rei que governa sobre todos. Jeremias também compartilhou uma mensagem de esperança para algumas dessas nações. Deus prometeu que seu povo seria bem-sucedido novamente no futuro. Após o tempo de julgamento, Deus os abençoaria novamente.</p>",
    "associations": {
      "passage": [
        {
          "start_ref": "24046001",
          "start_ref_usfm": "JER 46:1",
          "end_ref": "24049039",
          "end_ref_usfm": "JER 49:39"
        }
      ],
      "resource": [
        {
          "reference_id": 108267,
          "content_id": 145776,
          "resource_code": "BiblicaStudyNotesKeyTerms",
          "label": "Filisteus",
          "language": "por"
        },
        {
          "reference_id": 108397,
          "content_id": 145906,
          "resource_code": "BiblicaStudyNotesKeyTerms",
          "label": "Moabe",
          "language": "por"
        },
        {
          "reference_id": 108411,
          "content_id": 145920,
          "resource_code": "BiblicaStudyNotesKeyTerms",
          "label": "Edom",
          "language": "por"
        },
        {
          "reference_id": 108412,
          "content_id": 145921,
          "resource_code": "BiblicaStudyNotesKeyTerms",
          "label": "Amonitas",
          "language": "por"
        },
        {
          "reference_id": 108540,
          "content_id": 146049,
          "resource_code": "BiblicaStudyNotesKeyTerms",
          "label": "Damasco",
          "language": "por"
        }
      ]
    }
  },
  {
    "content_id": 297376,
    "reference_id": 109283,
    "title": "Jeremias 50.1–51.64",
    "media_type": "Text",
    "index_reference": "24050001-24051064",
    "language": "por",
    "content": "<p>No capítulo 25, Jeremias anunciou que Deus julgaria os babilônios. As mensagens completas de julgamento contra Babilônia estão registradas nos capítulos 50 e 51. Jeremias escreveu essas mensagens em um rolo. O irmão de Baruque deveria lê-las em voz alta na Babilônia. Depois, ele deveria afundar o rolo no <span data-bnType=\"resourceReference\" data-resourceId=\"108554\" data-resourceType=\"BiblicaStudyNotesKeyTerms\">Rio Eufrates</span>. Esta foi uma ação de profecia. Era um sinal de que Deus realizaria o que as mensagens falavam. Jeremias anunciou essas mensagens de julgamento antes mesmo de Nabucodonosor destruir Jerusalém. Os exércitos babilônios eram a ferramenta de Deus para trazer julgamento contra outras nações. Mas o povo e os líderes da Babilônia não reconheceram a verdadeira razão de seu sucesso. O poder de Deus lhes deu sucesso. Em vez disso, os babilônios honraram seus falsos deuses. Eles se enriqueceram tratando mal outros grupos de pessoas. Trabalharam arduamente para tornar suas muralhas grossas e altas. Isso mostrava que confiavam em seu governo e exército para mantê-los seguros. Deus falou sobre Babilônia alcançando até os <span data-bnType=\"resourceReference\" data-resourceId=\"108201\" data-resourceType=\"BiblicaStudyNotesKeyTerms\">céus</span>. Isso era uma maneira de descrever o quão orgulhosos eles eram. Isso era como a torre construída na cidade chamada Babel (Gênesis 11.1–9). As pessoas que construíram aquela torre queriam que ela chegasse ao céu. Deus deixou claro que alcançar os céus não manteria Babilônia segura. Três vezes Deus exortou seu povo a fugir da Babilônia. Ele não queria que eles fossem destruídos junto com Babilônia. A Babilônia, seria feito com ela o que tinha feito a outros. Isso concordava com uma lei da Lei de Moisés registrada em Levítico 24.19. Tudo no céu e na terra se alegraria quando Babilônia fosse punida. Isso porque Babilônia havia causado sofrimento a muitas pessoas e lugares. Eles ficariam felizes quando Babilônia não pudesse mais causar dano. Algumas das promessas de Deus para punir Babilônia se cumpriram quando a <span data-bnType=\"resourceReference\" data-resourceId=\"108509\" data-resourceType=\"BiblicaStudyNotesKeyTerms\">Pérsia</span> tomou o controle de Babilônia. Os escritores do Novo Testamento entenderam que algumas das promessas se cumpririam no futuro. Em Apocalipse capítulo 18, <span data-bnType=\"resourceReference\" data-resourceId=\"108542\" data-resourceType=\"BiblicaStudyNotesKeyTerms\">João</span> falou sobre essas mensagens de julgamento contra Babilônia. João usou Babilônia como uma forma de falar sobre outros governos orgulhosos. Babilônia foi o exemplo de como Deus puniria governos que tratassem mal o povo de Deus.</p>",
    "associations": {
      "passage": [
        {
          "start_ref": "24050001",
          "start_ref_usfm": "JER 50:1",
          "end_ref": "24051064",
          "end_ref_usfm": "JER 51:64"
        }
      ],
      "resource": [
        {
          "reference_id": 108201,
          "content_id": 145710,
          "resource_code": "BiblicaStudyNotesKeyTerms",
          "label": "Céu",
          "language": "por"
        },
        {
          "reference_id": 108509,
          "content_id": 146018,
          "resource_code": "BiblicaStudyNotesKeyTerms",
          "label": "Pérsia",
          "language": "por"
        },
        {
          "reference_id": 108542,
          "content_id": 146051,
          "resource_code": "BiblicaStudyNotesKeyTerms",
          "label": "João",
          "language": "por"
        },
        {
          "reference_id": 108554,
          "content_id": 146063,
          "resource_code": "BiblicaStudyNotesKeyTerms",
          "label": "Rio Eufrates",
          "language": "por"
        }
      ]
    }
  },
  {
    "content_id": 297377,
    "reference_id": 109284,
    "title": "Jeremias 52.1–34",
    "media_type": "Text",
    "index_reference": "24052001-24052034",
    "language": "por",
    "content": "<p>Jeremias havia falado mensagens de julgamento sobre Jerusalém sendo destruída por exércitos babilônicos. Ele havia falado essas mensagens inúmeras vezes por muitos anos. O povo e os líderes do reino do sul se recusaram a acreditar nele. A história de Babilônia tomando controle de Jerusalém foi contada em Jeremias capítulo 39. Esta história também foi registrada em 2 Reis capítulo 24 e 2 Crônicas capítulo 36. A história foi contada novamente como o último capítulo do livro de Jeremias. Isso deixou muito claro que Jeremias havia falado a verdade. Ele havia falado mensagens de Deus. As mensagens de Deus podiam ser confiadas.</p>",
    "associations": {
      "passage": [
        {
          "start_ref": "24052001",
          "start_ref_usfm": "JER 52:1",
          "end_ref": "24052034",
          "end_ref_usfm": "JER 52:34"
        }
      ],
      "resource": []
    }
  }
]