[
  {
    "content_id": 368977,
    "reference_id": 109303,
    "title": "योएल 1:1–20",
    "media_type": "Text",
    "index_reference": "29001001-29001020",
    "language": "hin",
    "content": "<p><span data-bnType=\"resourceReference\" data-resourceId=\"108480\" data-resourceType=\"BiblicaStudyNotesKeyTerms\">दक्षिणी राज्य</span> के लोग बहुत दुखी थे। <span data-bnType=\"resourceReference\" data-resourceId=\"108199\" data-resourceType=\"BiblicaStudyNotesKeyTerms\">परमेश्वर</span> ने उनके देश में टिड्डियों की एक महामारी भेजी थी।</p><p>यह उस टिड्डियों की महामारी के समान था जो परमेश्वर ने <span data-bnType=\"resourceReference\" data-resourceId=\"108251\" data-resourceType=\"BiblicaStudyNotesKeyTerms\">मिस्र</span> में भेजी थी। वह <span data-bnType=\"resourceReference\" data-resourceId=\"108308\" data-resourceType=\"BiblicaStudyNotesKeyTerms\">दस विपत्तियों</span> के समय की बात थी। योएल के समय में, टिड्डियों ने दक्षिणी राज्य की सभी फसलों को नष्ट कर दिया।</p><p>योएल ने इस घटना को <span data-bnType=\"resourceReference\" data-resourceId=\"108571\" data-resourceType=\"BiblicaStudyNotesKeyTerms\">प्रभु का दिन</span> कहा। इसका अर्थ था कि परमेश्वर अपने लोगों (<span data-bnType=\"resourceReference\" data-resourceId=\"108199\" data-resourceType=\"BiblicaStudyNotesKeyTerms\">परमेश्वर के लोग</span>) के खिलाफ <span data-bnType=\"resourceReference\" data-resourceId=\"108233\" data-resourceType=\"BiblicaStudyNotesKeyTerms\">न्याय</span> लाये थे ।</p><p>योएल ने परमेश्वर के लोगों से आग्रह किया कि वे रोएं, भोजन न करें और परमेश्वर को पुकारें। शोक मनाना, <span data-bnType=\"resourceReference\" data-resourceId=\"108456\" data-resourceType=\"BiblicaStudyNotesKeyTerms\">उपवास</span> करना और <span data-bnType=\"resourceReference\" data-resourceId=\"108227\" data-resourceType=\"BiblicaStudyNotesKeyTerms\">प्रार्थना</span> करना यह दिखाने के तरीके थे कि लोग <span data-bnType=\"resourceReference\" data-resourceId=\"108195\" data-resourceType=\"BiblicaStudyNotesKeyTerms\">पाप</span> से दूर हो गए। इन कार्यों ने दिखाया कि लोगों ने <span data-bnType=\"resourceReference\" data-resourceId=\"108346\" data-resourceType=\"BiblicaStudyNotesKeyTerms\">पापों का पश्चाताप</span> किया और परमेश्वर की ओर लौट आए।</p>",
    "associations": {
      "passage": [
        {
          "start_ref": "29001001",
          "start_ref_usfm": "JOL 1:1",
          "end_ref": "29001020",
          "end_ref_usfm": "JOL 1:20"
        }
      ],
      "resource": [
        {
          "reference_id": 108195,
          "content_id": 183089,
          "resource_code": "BiblicaStudyNotesKeyTerms",
          "label": "पाप",
          "language": "hin"
        },
        {
          "reference_id": 108199,
          "content_id": 183093,
          "resource_code": "BiblicaStudyNotesKeyTerms",
          "label": "परमेश्वर",
          "language": "hin"
        },
        {
          "reference_id": 108227,
          "content_id": 183121,
          "resource_code": "BiblicaStudyNotesKeyTerms",
          "label": "प्रार्थना",
          "language": "hin"
        },
        {
          "reference_id": 108233,
          "content_id": 183127,
          "resource_code": "BiblicaStudyNotesKeyTerms",
          "label": "न्याय ",
          "language": "hin"
        },
        {
          "reference_id": 108251,
          "content_id": 183145,
          "resource_code": "BiblicaStudyNotesKeyTerms",
          "label": "मिस्र",
          "language": "hin"
        },
        {
          "reference_id": 108302,
          "content_id": 183196,
          "resource_code": "Unknown",
          "label": "परमेश्वर के लोग ",
          "language": "hin"
        },
        {
          "reference_id": 108308,
          "content_id": 183202,
          "resource_code": "BiblicaStudyNotesKeyTerms",
          "label": "दस विपत्तियाँ ",
          "language": "hin"
        },
        {
          "reference_id": 108346,
          "content_id": 183240,
          "resource_code": "BiblicaStudyNotesKeyTerms",
          "label": "पश्चाताप",
          "language": "hin"
        },
        {
          "reference_id": 108456,
          "content_id": 183350,
          "resource_code": "BiblicaStudyNotesKeyTerms",
          "label": "उपवास",
          "language": "hin"
        },
        {
          "reference_id": 108480,
          "content_id": 183374,
          "resource_code": "BiblicaStudyNotesKeyTerms",
          "label": "दक्षिणी राज्य",
          "language": "hin"
        },
        {
          "reference_id": 108571,
          "content_id": 183465,
          "resource_code": "BiblicaStudyNotesKeyTerms",
          "label": "प्रभु का दिन",
          "language": "hin"
        }
      ]
    }
  },
  {
    "content_id": 368978,
    "reference_id": 109304,
    "title": "जोएल 2:1–27",
    "media_type": "Text",
    "index_reference": "29002001-29002027",
    "language": "hin",
    "content": "<p>योएल <span data-bnType=\"resourceReference\" data-resourceId=\"108416\" data-resourceType=\"BiblicaStudyNotesKeyTerms\">भविष्यद्वक्ता </span>ने टिड्डियों की सेना के बारे में <span data-bnType=\"resourceReference\" data-resourceId=\"108534\" data-resourceType=\"BiblicaStudyNotesKeyTerms\">न्याय का संदेश</span> साझा किया।</p><p>योएल ने संदेश को एक <span data-bnType=\"resourceReference\" data-resourceId=\"108204\" data-resourceType=\"BiblicaStudyNotesKeyTerms\">कविता</span> के रूप में साझा किया। सेना के आगमन के समय को <span data-bnType=\"resourceReference\" data-resourceId=\"108226\" data-resourceType=\"BiblicaStudyNotesKeyTerms\">प्रभु</span> का दिन कहा गया था।</p><p>योएल ने इस सेना की टिड्डियों का वर्णन करने के लिए<span data-bnType=\"resourceReference\" data-resourceId=\"108541\" data-resourceType=\"BiblicaStudyNotesKeyTerms\"> अंतकालीन लेखन</span> का उपयोग किया। यह वही टिड्डियों का प्रकोप हो सकता है जिसके बारे में अध्याय 1 में बात की गई है। या यह आने वाले युद्ध के बारे में बात करने का एक तरीका हो सकता है।</p><p>टिड्डियाँ शायद उन <span data-bnType=\"resourceReference\" data-resourceId=\"108202\" data-resourceType=\"BiblicaStudyNotesKeyTerms\">मनुष्यों</span> के लिए संकेत थीं जो सैनिक थे। संदेश का उद्देश्य लोगों को यह प्रेरित करना था कि वे अपने <span data-bnType=\"resourceReference\" data-resourceId=\"108419\" data-resourceType=\"BiblicaStudyNotesKeyTerms\">हृदयों</span> को नम्र होने दें।</p><p>इसका मतलब यह समझना था कि पाप कितना भयानक है। इसका अर्थ था पाप के बारे में बहुत दुखी होना था। इसका अर्थ था अब और पाप न करना चाहना बल्कि परमेश्वर के मार्गों का अनुसरण करना चाहना।</p><p><span data-bnType=\"resourceReference\" data-resourceId=\"108328\" data-resourceType=\"BiblicaStudyNotesKeyTerms\">सीनै पर्वत की वाचा</span> में परमेश्वर ने समझाया था कि वे चाहते हैं कि उनके लोग कैसे जीवन व्यतीत करें।</p><p>योएल ने यह संदेश सुनाया कि लोगों के पश्चाताप करने के बाद क्या होगा। दक्षिणी राज्य के पौधे, पशु और लोग फिर से <span data-bnType=\"resourceReference\" data-resourceId=\"108379\" data-resourceType=\"BiblicaStudyNotesKeyTerms\">वाचा की आशीषों</span> का आनंद लें सकेंगे। परमेश्वर के लोग उनकी एकमात्र सच्चे परमेश्वर के रूप में आराधना और सेवा करेंगे।</p>",
    "associations": {
      "passage": [
        {
          "start_ref": "29002001",
          "start_ref_usfm": "JOL 2:1",
          "end_ref": "29002027",
          "end_ref_usfm": "JOL 2:27"
        }
      ],
      "resource": [
        {
          "reference_id": 108202,
          "content_id": 183096,
          "resource_code": "BiblicaStudyNotesKeyTerms",
          "label": "मनुष्य",
          "language": "hin"
        },
        {
          "reference_id": 108204,
          "content_id": 183098,
          "resource_code": "BiblicaStudyNotesKeyTerms",
          "label": "कविता",
          "language": "hin"
        },
        {
          "reference_id": 108226,
          "content_id": 183120,
          "resource_code": "BiblicaStudyNotesKeyTerms",
          "label": "परमेश्वर",
          "language": "hin"
        },
        {
          "reference_id": 108328,
          "content_id": 183222,
          "resource_code": "BiblicaStudyNotesKeyTerms",
          "label": "सीनै पहाड़ की वाचा",
          "language": "hin"
        },
        {
          "reference_id": 108379,
          "content_id": 183273,
          "resource_code": "BiblicaStudyNotesKeyTerms",
          "label": "वाचा कि आशीषें",
          "language": "hin"
        },
        {
          "reference_id": 108416,
          "content_id": 183310,
          "resource_code": "BiblicaStudyNotesKeyTerms",
          "label": "नबी",
          "language": "hin"
        },
        {
          "reference_id": 108419,
          "content_id": 183313,
          "resource_code": "BiblicaStudyNotesKeyTerms",
          "label": "हृदय",
          "language": "hin"
        },
        {
          "reference_id": 108534,
          "content_id": 183428,
          "resource_code": "BiblicaStudyNotesKeyTerms",
          "label": "न्याय के संदेश",
          "language": "hin"
        },
        {
          "reference_id": 108541,
          "content_id": 183435,
          "resource_code": "BiblicaStudyNotesKeyTerms",
          "label": "अंत समय के  लेख",
          "language": "hin"
        }
      ]
    }
  },
  {
    "content_id": 368979,
    "reference_id": 109305,
    "title": "योएल 2:28–3:21",
    "media_type": "Text",
    "index_reference": "29002028-29003021",
    "language": "hin",
    "content": "<p>योएल ने दक्षिणी राज्य के चारों ओर के राष्ट्रों के खिलाफ न्याय के संदेश साझा किए। इस न्याय के समय को प्रभु का दिन कहा गया था। योएल ने इस दिन का वर्णन करने के लिए अंतकालीन लेखन का उपयोग किया था। यह कुछ के लिए न्याय का समय था और दूसरों के लिए आशीष का समय था। परमेश्वर ने वादा किया कि वे उन राष्ट्रों का न्याय करेंगे जिन्होंने उनके लोगों के साथ बुरा व्यवहार किया था। इन राष्ट्रों के पापों पर<span data-bnType=\"resourceReference\" data-resourceId=\"108500\" data-resourceType=\"BiblicaStudyNotesKeyTerms\"> परमेश्वर का क्रोध</span> एक <span>दाख रसकुण्ड</span> की तरह था। राष्ट्र उसमें दाख की तरह कुचले जाएंगे। योएल ने इसी तरह उन्हें बुरे कार्य करने के लिए दंडित किये जाने का वर्णन किया।</p><p>यशायाह के संदेश अध्याय 1 में दिखाते हैं कि परमेश्वर अपने लोगों के पाप के कारण न्याय लाए। अध्याय 2 और 3 के संदेश परमेश्वर के बारे में कुछ और दिखाते हैं। परमेश्वर सभी जातियों के समूहों के पाप के कारण न्याय लाते हैं। और परमेश्वर की आशीषें उन सभी जातियों के समूहों के लिए हैं जो उनकी आज्ञा का पालन करते हैं। <span data-bnType=\"resourceReference\" data-resourceId=\"108229\" data-resourceType=\"BiblicaStudyNotesKeyTerms\">परमेश्वर ने चुना</span> कि वे सिय्योन में निवास करें। <span data-bnType=\"resourceReference\" data-resourceId=\"108464\" data-resourceType=\"BiblicaStudyNotesKeyTerms\">यरूशलेम</span> का एक और नाम सिय्योन है। इसका अर्थ है कि परमेश्वर ने वहां लोगों के बीच अपनी उपस्थिति को प्रकट किया। परमेश्वर की उपस्थिति उनके लोगों के लिए सुरक्षा, स्वास्थ्य, <span data-bnType=\"resourceReference\" data-resourceId=\"108211\" data-resourceType=\"BiblicaStudyNotesKeyTerms\">शांति</span> और <span data-bnType=\"resourceReference\" data-resourceId=\"108212\" data-resourceType=\"BiblicaStudyNotesKeyTerms\">विश्राम</span> लाती है।</p><p>ये आशीषें केवल <span data-bnType=\"resourceReference\" data-resourceId=\"108280\" data-resourceType=\"BiblicaStudyNotesKeyTerms\">इस्राएल</span> के लोगों के लिए नहीं थीं। परमेश्वर ने वादा किया था कि <span data-bnType=\"resourceReference\" data-resourceId=\"108417\" data-resourceType=\"BiblicaStudyNotesKeyTerms\">मन्दिर </span>से एक सोता बहेगा। <span data-bnType=\"resourceReference\" data-resourceId=\"108555\" data-resourceType=\"BiblicaStudyNotesKeyTerms\">यहेजकेल</span> ने भी मन्दिर से बहने वाली नदी के बारे में बात की (यहेजकेल 47:1–12)। मन्दिर से बहने वाला जल आशीष का संकेत था। यह उस <span data-bnType=\"resourceReference\" data-resourceId=\"108559\" data-resourceType=\"BiblicaStudyNotesKeyTerms\">जीवित जल</span> का भी संकेत था जो परमेश्वर को जानने से आता है। योएल ने दिखाया कि यह आशीष और जीवन उन सभी लोगों के लिए था जो परमेश्वर की सेवा करते हैं।</p><p>परमेश्वर उन पर अपनी आत्मा उण्डेलेगे। इसका अर्थ था कि <span data-bnType=\"resourceReference\" data-resourceId=\"108388\" data-resourceType=\"BiblicaStudyNotesKeyTerms\">पवित्र आत्मा</span> उनके लोगों के भीतर होगा। यह <span data-bnType=\"resourceReference\" data-resourceId=\"108553\" data-resourceType=\"BiblicaStudyNotesKeyTerms\">नई वाचा</span> का हिस्सा था। कई वर्षों बाद <span data-bnType=\"resourceReference\" data-resourceId=\"108219\" data-resourceType=\"BiblicaStudyNotesKeyTerms\">यीशु</span> ने <span data-bnType=\"resourceReference\" data-resourceId=\"108375\" data-resourceType=\"BiblicaStudyNotesKeyTerms\">पिन्तेकुस्त</span> के दौरान अपने अनुयायियों के पास पवित्र आत्मा भेजा। <span data-bnType=\"resourceReference\" data-resourceId=\"108572\" data-resourceType=\"BiblicaStudyNotesKeyTerms\">पतरस</span> ने समझाया कि जब यह हुआ, तब योएल की <span data-bnType=\"resourceReference\" data-resourceId=\"108399\" data-resourceType=\"BiblicaStudyNotesKeyTerms\">भविष्यद्वाणी </span>का एक हिस्सा पूरा हुआ (प्रेरि 2:14–21)।</p>",
    "associations": {
      "passage": [
        {
          "start_ref": "29002028",
          "start_ref_usfm": "JOL 2:28",
          "end_ref": "29003021",
          "end_ref_usfm": "JOL 3:21"
        }
      ],
      "resource": [
        {
          "reference_id": 108211,
          "content_id": 183105,
          "resource_code": "BiblicaStudyNotesKeyTerms",
          "label": "शांति",
          "language": "hin"
        },
        {
          "reference_id": 108212,
          "content_id": 183106,
          "resource_code": "BiblicaStudyNotesKeyTerms",
          "label": "विश्राम",
          "language": "hin"
        },
        {
          "reference_id": 108219,
          "content_id": 183113,
          "resource_code": "BiblicaStudyNotesKeyTerms",
          "label": "यीशु ",
          "language": "hin"
        },
        {
          "reference_id": 108229,
          "content_id": 183123,
          "resource_code": "BiblicaStudyNotesKeyTerms",
          "label": "परमेश्वर चुनता है",
          "language": "hin"
        },
        {
          "reference_id": 108280,
          "content_id": 183174,
          "resource_code": "BiblicaStudyNotesKeyTerms",
          "label": "इस्राएल ",
          "language": "hin"
        },
        {
          "reference_id": 108375,
          "content_id": 183269,
          "resource_code": "BiblicaStudyNotesKeyTerms",
          "label": "पिन्तेकुस्त  ",
          "language": "hin"
        },
        {
          "reference_id": 108388,
          "content_id": 183282,
          "resource_code": "BiblicaStudyNotesKeyTerms",
          "label": "पवित्र आत्मा",
          "language": "hin"
        },
        {
          "reference_id": 108399,
          "content_id": 183293,
          "resource_code": "BiblicaStudyNotesKeyTerms",
          "label": "भविष्यवाणी",
          "language": "hin"
        },
        {
          "reference_id": 108417,
          "content_id": 183311,
          "resource_code": "BiblicaStudyNotesKeyTerms",
          "label": "मंदिर",
          "language": "hin"
        },
        {
          "reference_id": 108464,
          "content_id": 183358,
          "resource_code": "BiblicaStudyNotesKeyTerms",
          "label": "यरूशलेम",
          "language": "hin"
        },
        {
          "reference_id": 108500,
          "content_id": 183394,
          "resource_code": "BiblicaStudyNotesKeyTerms",
          "label": "परमेश्वर का क्रोध ",
          "language": "hin"
        },
        {
          "reference_id": 108553,
          "content_id": 183447,
          "resource_code": "BiblicaStudyNotesKeyTerms",
          "label": "नई वाचा",
          "language": "hin"
        },
        {
          "reference_id": 108555,
          "content_id": 183449,
          "resource_code": "BiblicaStudyNotesKeyTerms",
          "label": "यहेजकेल",
          "language": "hin"
        },
        {
          "reference_id": 108559,
          "content_id": 183453,
          "resource_code": "BiblicaStudyNotesKeyTerms",
          "label": "जीवन का जल",
          "language": "hin"
        },
        {
          "reference_id": 108572,
          "content_id": 183466,
          "resource_code": "BiblicaStudyNotesKeyTerms",
          "label": "पतरस",
          "language": "hin"
        }
      ]
    }
  }
]