[
  {
    "content_id": 296627,
    "reference_id": 108882,
    "title": "Romanos 1:1–17",
    "media_type": "Text",
    "index_reference": "45001001-45001017",
    "language": "spa",
    "content": "<p><span data-bnType=\"resourceReference\" data-resourceId=\"108102\" data-resourceType=\"BiblicaStudyNotesKeyTerms\">Pablo</span> ansiaba ver a los <span data-bnType=\"resourceReference\" data-resourceId=\"108077\" data-resourceType=\"BiblicaStudyNotesKeyTerms\">creyentes</span> en la ciudad de <span data-bnType=\"resourceReference\" data-resourceId=\"108047\" data-resourceType=\"BiblicaStudyNotesKeyTerms\">Roma</span>. Había intentado visitarlos muchas veces, pero siempre se le había impedido ir. Así que escribió una carta para animarlos con las <span data-bnType=\"resourceReference\" data-resourceId=\"108043\" data-resourceType=\"BiblicaStudyNotesKeyTerms\">buenas noticias</span> sobre <span data-bnType=\"resourceReference\" data-resourceId=\"108219\" data-resourceType=\"BiblicaStudyNotesKeyTerms\">Jesús</span>. Pablo era un <span data-bnType=\"resourceReference\" data-resourceId=\"108053\" data-resourceType=\"BiblicaStudyNotesKeyTerms\">apóstol</span>. Servía a Jesús <span data-bnType=\"resourceReference\" data-resourceId=\"108098\" data-resourceType=\"BiblicaStudyNotesKeyTerms\">Cristo</span> el <span data-bnType=\"resourceReference\" data-resourceId=\"108329\" data-resourceType=\"BiblicaStudyNotesKeyTerms\">Señor</span> y <span data-bnType=\"resourceReference\" data-resourceId=\"108527\" data-resourceType=\"BiblicaStudyNotesKeyTerms\">Mesías</span>. Esto significa que seguía el ejemplo de Jesús de ser un <span data-bnType=\"resourceReference\" data-resourceId=\"108059\" data-resourceType=\"BiblicaStudyNotesKeyTerms\">líder sirviente</span>. El <span data-bnType=\"resourceReference\" data-resourceId=\"108208\" data-resourceType=\"BiblicaStudyNotesKeyTerms\">trabajo</span> de Pablo era predicar las buenas nuevas tanto a <span data-bnType=\"resourceReference\" data-resourceId=\"108503\" data-resourceType=\"BiblicaStudyNotesKeyTerms\">judíos</span> como a <span data-bnType=\"resourceReference\" data-resourceId=\"108547\" data-resourceType=\"BiblicaStudyNotesKeyTerms\">gentiles</span>. Jesús era judío, y <span data-bnType=\"resourceReference\" data-resourceId=\"108199\" data-resourceType=\"BiblicaStudyNotesKeyTerms\">Dios</span> había hecho promesas sobre él en las Escrituras judías. Las Escrituras son la <span data-bnType=\"resourceReference\" data-resourceId=\"108199\" data-resourceType=\"BiblicaStudyNotesKeyTerms\">palabra de Dios</span>. Dios cumplió estas promesas cuando resucitó a Jesús de entre los muertos. La <span data-bnType=\"resourceReference\" data-resourceId=\"108568\" data-resourceType=\"BiblicaStudyNotesKeyTerms\">resurrección</span> de Jesús mostró el poder de Dios para salvar tanto a judíos como a gentiles. Dios tiene el poder de salvar a todos a través del <span data-bnType=\"resourceReference\" data-resourceId=\"108256\" data-resourceType=\"BiblicaStudyNotesKeyTerms\">sacrificio</span> de Jesús. ¡Estas son las buenas noticias! Cuando las personas creen en estas buenas noticias, muestran que tienen <span data-bnType=\"resourceReference\" data-resourceId=\"108232\" data-resourceType=\"BiblicaStudyNotesKeyTerms\">fe</span> en Dios. Tener fe significa estar comprometido con Dios y confiar en él. Aquellos que tienen fe son hechos <span data-bnType=\"resourceReference\" data-resourceId=\"108254\" data-resourceType=\"BiblicaStudyNotesKeyTerms\">justos ante Dios</span>.</p>",
    "associations": {
      "passage": [
        {
          "start_ref": "45001001",
          "start_ref_usfm": "ROM 1:1",
          "end_ref": "45001017",
          "end_ref_usfm": "ROM 1:17"
        }
      ],
      "resource": [
        {
          "reference_id": 108043,
          "content_id": 232012,
          "resource_code": "BiblicaStudyNotesKeyTerms",
          "label": "Buenas noticias",
          "language": "spa"
        },
        {
          "reference_id": 108047,
          "content_id": 232016,
          "resource_code": "BiblicaStudyNotesKeyTerms",
          "label": "Roma",
          "language": "spa"
        },
        {
          "reference_id": 108059,
          "content_id": 232028,
          "resource_code": "BiblicaStudyNotesKeyTerms",
          "label": "Líder que sirve",
          "language": "spa"
        },
        {
          "reference_id": 108098,
          "content_id": 232067,
          "resource_code": "BiblicaStudyNotesKeyTerms",
          "label": "Cristo",
          "language": "spa"
        },
        {
          "reference_id": 108053,
          "content_id": 232022,
          "resource_code": "BiblicaStudyNotesKeyTerms",
          "label": "Apóstoles",
          "language": "spa"
        },
        {
          "reference_id": 108077,
          "content_id": 232046,
          "resource_code": "BiblicaStudyNotesKeyTerms",
          "label": "Creyente",
          "language": "spa"
        },
        {
          "reference_id": 108102,
          "content_id": 232071,
          "resource_code": "BiblicaStudyNotesKeyTerms",
          "label": "Pablo",
          "language": "spa"
        },
        {
          "reference_id": 108199,
          "content_id": 232168,
          "resource_code": "BiblicaStudyNotesKeyTerms",
          "label": "Dios",
          "language": "spa"
        },
        {
          "reference_id": 108200,
          "content_id": 232169,
          "resource_code": "Unknown",
          "label": "La palabra de Dios",
          "language": "spa"
        },
        {
          "reference_id": 108208,
          "content_id": 232177,
          "resource_code": "BiblicaStudyNotesKeyTerms",
          "label": "Trabajo",
          "language": "spa"
        },
        {
          "reference_id": 108219,
          "content_id": 232188,
          "resource_code": "BiblicaStudyNotesKeyTerms",
          "label": "Jesús",
          "language": "spa"
        },
        {
          "reference_id": 108232,
          "content_id": 232201,
          "resource_code": "BiblicaStudyNotesKeyTerms",
          "label": "Fe",
          "language": "spa"
        },
        {
          "reference_id": 108254,
          "content_id": 232223,
          "resource_code": "BiblicaStudyNotesKeyTerms",
          "label": "Bien con Dios",
          "language": "spa"
        },
        {
          "reference_id": 108256,
          "content_id": 232225,
          "resource_code": "BiblicaStudyNotesKeyTerms",
          "label": "Sacrificio",
          "language": "spa"
        },
        {
          "reference_id": 108329,
          "content_id": 232298,
          "resource_code": "BiblicaStudyNotesKeyTerms",
          "label": "Señor - Gobernante",
          "language": "spa"
        },
        {
          "reference_id": 108503,
          "content_id": 232472,
          "resource_code": "BiblicaStudyNotesKeyTerms",
          "label": "Judío",
          "language": "spa"
        },
        {
          "reference_id": 108527,
          "content_id": 232496,
          "resource_code": "BiblicaStudyNotesKeyTerms",
          "label": "Mesías",
          "language": "spa"
        },
        {
          "reference_id": 108547,
          "content_id": 232516,
          "resource_code": "BiblicaStudyNotesKeyTerms",
          "label": "Gentil",
          "language": "spa"
        },
        {
          "reference_id": 108568,
          "content_id": 232537,
          "resource_code": "BiblicaStudyNotesKeyTerms",
          "label": "Resurrección",
          "language": "spa"
        }
      ]
    }
  },
  {
    "content_id": 296628,
    "reference_id": 108883,
    "title": "Romanos 1:18–32",
    "media_type": "Text",
    "index_reference": "45001018-45001032",
    "language": "spa",
    "content": "<p>Dios es el Creador de todas las cosas. El <span data-bnType=\"resourceReference\" data-resourceId=\"108215\" data-resourceType=\"BiblicaStudyNotesKeyTerms\">mundo</span> que creó es prueba de su poder y <span data-bnType=\"resourceReference\" data-resourceId=\"108348\" data-resourceType=\"BiblicaStudyNotesKeyTerms\">gloria</span>. Esto debería hacer que los <span data-bnType=\"resourceReference\" data-resourceId=\"108202\" data-resourceType=\"BiblicaStudyNotesKeyTerms\">seres humanos</span> quisieran <span data-bnType=\"resourceReference\" data-resourceId=\"108332\" data-resourceType=\"BiblicaStudyNotesKeyTerms\">adorar solo a Dios</span> y agradecerle. Sin embargo, los seres humanos eligen no hacer esto. Ponen su esperanza y confianza en las cosas creadas. Se niegan a creer que Dios es bueno. Al decir no a quien Dios realmente es, eligen creer mentiras. Esto lleva a los seres humanos a vivir de maneras que son dañinas. Están llenos de <span data-bnType=\"resourceReference\" data-resourceId=\"108195\" data-resourceType=\"BiblicaStudyNotesKeyTerms\">pecado</span>. Van en contra del orden que Dios planeó para su mundo. Se lastiman a sí mismos, a otras personas y al resto de la <span data-bnType=\"resourceReference\" data-resourceId=\"108197\" data-resourceType=\"BiblicaStudyNotesKeyTerms\">creación</span>.</p>",
    "associations": {
      "passage": [
        {
          "start_ref": "45001018",
          "start_ref_usfm": "ROM 1:18",
          "end_ref": "45001032",
          "end_ref_usfm": "ROM 1:32"
        }
      ],
      "resource": [
        {
          "reference_id": 108195,
          "content_id": 232164,
          "resource_code": "BiblicaStudyNotesKeyTerms",
          "label": "Pecado",
          "language": "spa"
        },
        {
          "reference_id": 108197,
          "content_id": 232166,
          "resource_code": "BiblicaStudyNotesKeyTerms",
          "label": "Creación",
          "language": "spa"
        },
        {
          "reference_id": 108202,
          "content_id": 232171,
          "resource_code": "BiblicaStudyNotesKeyTerms",
          "label": "Seres humanos",
          "language": "spa"
        },
        {
          "reference_id": 108215,
          "content_id": 232184,
          "resource_code": "BiblicaStudyNotesKeyTerms",
          "label": "Mundo",
          "language": "spa"
        },
        {
          "reference_id": 108332,
          "content_id": 232301,
          "resource_code": "BiblicaStudyNotesKeyTerms",
          "label": "Adorar solo a Dios",
          "language": "spa"
        },
        {
          "reference_id": 108348,
          "content_id": 232317,
          "resource_code": "BiblicaStudyNotesKeyTerms",
          "label": "Gloria",
          "language": "spa"
        }
      ]
    }
  },
  {
    "content_id": 296629,
    "reference_id": 108884,
    "title": "Romanos 2:1–16",
    "media_type": "Text",
    "index_reference": "45002001-45002016",
    "language": "spa",
    "content": "<p>Dios dio al pueblo judío sus instrucciones en la ley. Pablo estaba hablando de la <span data-bnType=\"resourceReference\" data-resourceId=\"108335\" data-resourceType=\"BiblicaStudyNotesKeyTerms\">Ley de Moisés</span>. Debido a esto, algunos judíos pensaban que eran mejores que los gentiles. Juzgaban a los gentiles de manera injusta. Los gentiles no habían recibido la ley. Aun así, algunos gentiles vivían de acuerdo con los caminos de Dios como se describe en la ley. Y algunos judíos que conocían la Ley de Moisés no la obedecían. Pablo dejó claro que las personas no deben juzgarse unas a otras. Solo Dios puede juzgar a las personas de manera justa. Su <span data-bnType=\"resourceReference\" data-resourceId=\"108233\" data-resourceType=\"BiblicaStudyNotesKeyTerms\">juicio</span> se basará en cómo han vivido sus vidas. Jesús juzgará hasta la forma en que las personas piensan. Algunas personas honran a Dios y hacen <span data-bnType=\"resourceReference\" data-resourceId=\"108060\" data-resourceType=\"BiblicaStudyNotesKeyTerms\">buenas obras</span> que ayudan a otros. Esto muestra que tienen fe en Jesús. Estas personas recibirán <span data-bnType=\"resourceReference\" data-resourceId=\"108569\" data-resourceType=\"BiblicaStudyNotesKeyTerms\">vida eterna</span>. Otros le dicen no a Dios y solo se preocupan por sí mismos. Estas personas recibirán <span data-bnType=\"resourceReference\" data-resourceId=\"108500\" data-resourceType=\"BiblicaStudyNotesKeyTerms\">la ira de Dios</span> contra el pecado y el mal. Dios es muy amable con las personas y quiere que ellas se aparten de sus pecados. Cuando las personas <span data-bnType=\"resourceReference\" data-resourceId=\"108346\" data-resourceType=\"BiblicaStudyNotesKeyTerms\">se arrepienten</span>, pueden confiar en que Dios les dará una vida que la muerte no puede destruir.</p>",
    "associations": {
      "passage": [
        {
          "start_ref": "45002001",
          "start_ref_usfm": "ROM 2:1",
          "end_ref": "45002016",
          "end_ref_usfm": "ROM 2:16"
        }
      ],
      "resource": [
        {
          "reference_id": 108060,
          "content_id": 232029,
          "resource_code": "BiblicaStudyNotesKeyTerms",
          "label": "Buenas obras",
          "language": "spa"
        },
        {
          "reference_id": 108233,
          "content_id": 232202,
          "resource_code": "BiblicaStudyNotesKeyTerms",
          "label": "Juicio",
          "language": "spa"
        },
        {
          "reference_id": 108335,
          "content_id": 232304,
          "resource_code": "BiblicaStudyNotesKeyTerms",
          "label": "Ley de Moisés",
          "language": "spa"
        },
        {
          "reference_id": 108346,
          "content_id": 232315,
          "resource_code": "BiblicaStudyNotesKeyTerms",
          "label": "Arrepentir",
          "language": "spa"
        },
        {
          "reference_id": 108500,
          "content_id": 232469,
          "resource_code": "BiblicaStudyNotesKeyTerms",
          "label": "La ira de Dios",
          "language": "spa"
        },
        {
          "reference_id": 108569,
          "content_id": 232538,
          "resource_code": "BiblicaStudyNotesKeyTerms",
          "label": "Vida eterna",
          "language": "spa"
        }
      ]
    }
  },
  {
    "content_id": 296630,
    "reference_id": 108885,
    "title": "Romanos 2:17–29",
    "media_type": "Text",
    "index_reference": "45002017-45002029",
    "language": "spa",
    "content": "<p>Muchos judíos en la época de Pablo pensaban que el pueblo de <span data-bnType=\"resourceReference\" data-resourceId=\"108280\" data-resourceType=\"BiblicaStudyNotesKeyTerms\">Israel</span> era especial. Pensaban que eran mejores que otros grupos de personas. Creían esto porque <span data-bnType=\"resourceReference\" data-resourceId=\"108229\" data-resourceType=\"BiblicaStudyNotesKeyTerms\">Dios eligió</span> hacer el <span data-bnType=\"resourceReference\" data-resourceId=\"108328\" data-resourceType=\"BiblicaStudyNotesKeyTerms\">pacto del Monte Sinaí</span> con la <span data-bnType=\"resourceReference\" data-resourceId=\"108268\" data-resourceType=\"BiblicaStudyNotesKeyTerms\">línea familiar</span> de <span data-bnType=\"resourceReference\" data-resourceId=\"108220\" data-resourceType=\"BiblicaStudyNotesKeyTerms\">Jacob</span>. Pero los judíos no habían sido fieles al <span data-bnType=\"resourceReference\" data-resourceId=\"108237\" data-resourceType=\"BiblicaStudyNotesKeyTerms\">pacto</span>. No habían obedecido fielmente los <span data-bnType=\"resourceReference\" data-resourceId=\"108331\" data-resourceType=\"BiblicaStudyNotesKeyTerms\">Diez Mandamientos</span> y la Ley de Moisés. El resultado fue que no habían compartido la <span data-bnType=\"resourceReference\" data-resourceId=\"108546\" data-resourceType=\"BiblicaStudyNotesKeyTerms\">luz</span> de Dios con otros grupos de personas. Pablo dijo que los judíos no eran mejores que los demás. Las leyes escritas y un cuerpo <span data-bnType=\"resourceReference\" data-resourceId=\"108257\" data-resourceType=\"BiblicaStudyNotesKeyTerms\">circuncidado</span> no hacen que alguien sea aceptable a Dios. Lo que importa es que las personas confíen en Dios con sus <span data-bnType=\"resourceReference\" data-resourceId=\"108419\" data-resourceType=\"BiblicaStudyNotesKeyTerms\">corazones</span>. Eso es lo que Pablo quería decir sobre la circuncisión de los corazones de las personas. Dios busca personas que confíen en él para cambiar sus corazones. El <span data-bnType=\"resourceReference\" data-resourceId=\"108388\" data-resourceType=\"BiblicaStudyNotesKeyTerms\">Espíritu Santo</span> les da poder para vivir como Dios quiere que vivan. Dios está muy satisfecho con esto.</p>",
    "associations": {
      "passage": [
        {
          "start_ref": "45002017",
          "start_ref_usfm": "ROM 2:17",
          "end_ref": "45002029",
          "end_ref_usfm": "ROM 2:29"
        }
      ],
      "resource": [
        {
          "reference_id": 108220,
          "content_id": 232189,
          "resource_code": "BiblicaStudyNotesKeyTerms",
          "label": "Línea familiar",
          "language": "spa"
        },
        {
          "reference_id": 108229,
          "content_id": 232198,
          "resource_code": "BiblicaStudyNotesKeyTerms",
          "label": "Dios elige",
          "language": "spa"
        },
        {
          "reference_id": 108237,
          "content_id": 232206,
          "resource_code": "BiblicaStudyNotesKeyTerms",
          "label": "Pacto",
          "language": "spa"
        },
        {
          "reference_id": 108257,
          "content_id": 232226,
          "resource_code": "BiblicaStudyNotesKeyTerms",
          "label": "Circuncisión",
          "language": "spa"
        },
        {
          "reference_id": 108268,
          "content_id": 232237,
          "resource_code": "BiblicaStudyNotesKeyTerms",
          "label": "Jacob",
          "language": "spa"
        },
        {
          "reference_id": 108280,
          "content_id": 232249,
          "resource_code": "BiblicaStudyNotesKeyTerms",
          "label": "Israel",
          "language": "spa"
        },
        {
          "reference_id": 108328,
          "content_id": 232297,
          "resource_code": "BiblicaStudyNotesKeyTerms",
          "label": "Pacto del Monte Sinaí",
          "language": "spa"
        },
        {
          "reference_id": 108331,
          "content_id": 232300,
          "resource_code": "BiblicaStudyNotesKeyTerms",
          "label": "Diez Mandamientos",
          "language": "spa"
        },
        {
          "reference_id": 108388,
          "content_id": 232357,
          "resource_code": "BiblicaStudyNotesKeyTerms",
          "label": "Espíritu Santo",
          "language": "spa"
        },
        {
          "reference_id": 108419,
          "content_id": 232388,
          "resource_code": "BiblicaStudyNotesKeyTerms",
          "label": "Corazón",
          "language": "spa"
        },
        {
          "reference_id": 108546,
          "content_id": 232515,
          "resource_code": "BiblicaStudyNotesKeyTerms",
          "label": "Luz",
          "language": "spa"
        }
      ]
    }
  },
  {
    "content_id": 296631,
    "reference_id": 108886,
    "title": "Romanos 3:1–20",
    "media_type": "Text",
    "index_reference": "45003001-45003020",
    "language": "spa",
    "content": "<p>Los judíos habían recibido el valioso regalo de las palabras y pactos de Dios. Dios fue fiel al pacto del <span data-bnType=\"resourceReference\" data-resourceId=\"108327\" data-resourceType=\"BiblicaStudyNotesKeyTerms\">Monte Sinaí</span>, pero los judíos no lo fueron. ¿Se había detenido el plan de Dios porque <span data-bnType=\"resourceReference\" data-resourceId=\"108302\" data-resourceType=\"BiblicaStudyNotesKeyTerms\">el pueblo de Dios</span> no fue fiel? No. Pablo explicó que Dios siempre es fiel y siempre se puede confiar en él. Cuando los humanos hacen cosas malas, no cambia la bondad de Dios de ninguna manera. Tener el pacto d<span>el Monte Sinaí no les daba a los judíos una ventaja sobre el pecado. Tanto judíos como gentiles están controlados por el poder del pecado. La Ley de Moisés ayudó a los judíos a entender las formas en que son culpables de pecado. Nadie puede ser liberado del poder del pecado por sí mismo.</span></p>",
    "associations": {
      "passage": [
        {
          "start_ref": "45003001",
          "start_ref_usfm": "ROM 3:1",
          "end_ref": "45003020",
          "end_ref_usfm": "ROM 3:20"
        }
      ],
      "resource": [
        {
          "reference_id": 108302,
          "content_id": 232271,
          "resource_code": "BiblicaStudyNotesKeyTerms",
          "label": "El pueblo de Dios",
          "language": "spa"
        },
        {
          "reference_id": 108327,
          "content_id": 232296,
          "resource_code": "BiblicaStudyNotesKeyTerms",
          "label": "Monte Sinaí",
          "language": "spa"
        }
      ]
    }
  },
  {
    "content_id": 296632,
    "reference_id": 108887,
    "title": "Romanos 3:21–31",
    "media_type": "Text",
    "index_reference": "45003021-45003031",
    "language": "spa",
    "content": "<p>Cuando las personas pecan, van en contra de lo que Dios quiere. Los humanos no pueden detener el poder del pecado en sus vidas tratando de obedecer a Dios. Esto significa que su relación con Dios está rota. Dios no quiere tener una relación rota con las personas. Pablo mostró cómo Dios trató el problema del pecado. Jesús sacrificó su propia vida para afrontar  el pecado y liberar a las personas de su poder. Esto muestra la <span data-bnType=\"resourceReference\" data-resourceId=\"108342\" data-resourceType=\"BiblicaStudyNotesKeyTerms\">misericordia</span> de Dios. Todas las personas que creen que Jesús hizo esto por ellas son hechas justas con Dios. Al tener fe en Jesús, son salvadas de ser <span data-bnType=\"resourceReference\" data-resourceId=\"108258\" data-resourceType=\"BiblicaStudyNotesKeyTerms\">esclavas</span> del pecado. Dios trata a las personas que confían en él como si no hubieran pecado. Esto es cierto tanto para judíos como para gentiles.</p>",
    "associations": {
      "passage": [
        {
          "start_ref": "45003021",
          "start_ref_usfm": "ROM 3:21",
          "end_ref": "45003031",
          "end_ref_usfm": "ROM 3:31"
        }
      ],
      "resource": [
        {
          "reference_id": 108258,
          "content_id": 232227,
          "resource_code": "BiblicaStudyNotesKeyTerms",
          "label": "Esclavos",
          "language": "spa"
        },
        {
          "reference_id": 108342,
          "content_id": 232311,
          "resource_code": "BiblicaStudyNotesKeyTerms",
          "label": "Misericordia",
          "language": "spa"
        }
      ]
    }
  },
  {
    "content_id": 296633,
    "reference_id": 108888,
    "title": "Romanos 4:1–25",
    "media_type": "Text",
    "index_reference": "45004001-45004025",
    "language": "spa",
    "content": "<p>Los judíos sabían que Dios había hecho un <span data-bnType=\"resourceReference\" data-resourceId=\"108253\" data-resourceType=\"BiblicaStudyNotesKeyTerms\">pacto con Abraham</span>. Dios le había prometido tierra para vivir y una familia muy grande. <span data-bnType=\"resourceReference\" data-resourceId=\"108243\" data-resourceType=\"BiblicaStudyNotesKeyTerms\">Abraham</span> no había hecho nada para merecer esta promesa. Abraham y <span data-bnType=\"resourceReference\" data-resourceId=\"108247\" data-resourceType=\"BiblicaStudyNotesKeyTerms\">Sara</span> eran muy viejos para tener hijos. Aun así, Abraham creía que Dios cumpliría su promesa. Tenía esperanza en Dios y fe en que Dios podía hacer cualquier cosa que quisiera. Dios estaba muy complacido de que Abraham le creyera. Dios hizo que Abraham estuviera en paz con él. Estar en paz con Dios es una bendición. Esta bendición es para todos los que tienen fe como la de Abraham. Las personas que tienen fe como la fe de Abraham también son hijos de Abraham. Son sus hijos incluso si no son de su línea familiar. Pablo explicó cómo la fe de Abraham está conectada con Jesús. El Dios en el que Abraham creía es el Dios que resucitó a Jesús de entre los muertos. Todos los que <span data-bnType=\"resourceReference\" data-resourceId=\"108255\" data-resourceType=\"BiblicaStudyNotesKeyTerms\">creen en</span> Jesús están en paz con Dios.</p>",
    "associations": {
      "passage": [
        {
          "start_ref": "45004001",
          "start_ref_usfm": "ROM 4:1",
          "end_ref": "45004025",
          "end_ref_usfm": "ROM 4:25"
        }
      ],
      "resource": [
        {
          "reference_id": 108243,
          "content_id": 232212,
          "resource_code": "BiblicaStudyNotesKeyTerms",
          "label": "Abraham",
          "language": "spa"
        },
        {
          "reference_id": 108247,
          "content_id": 232216,
          "resource_code": "BiblicaStudyNotesKeyTerms",
          "label": "Sara",
          "language": "spa"
        },
        {
          "reference_id": 108253,
          "content_id": 232222,
          "resource_code": "BiblicaStudyNotesKeyTerms",
          "label": "Pacto con Abraham",
          "language": "spa"
        },
        {
          "reference_id": 108255,
          "content_id": 232224,
          "resource_code": "BiblicaStudyNotesKeyTerms",
          "label": "Creer en",
          "language": "spa"
        }
      ]
    }
  },
  {
    "content_id": 296634,
    "reference_id": 108889,
    "title": "Romanos 5:1–11",
    "media_type": "Text",
    "index_reference": "45005001-45005011",
    "language": "spa",
    "content": "<p>Pablo describió que las bendiciones llegan al pueblo de Dios a través de Jesús. Ellos reciben su <span data-bnType=\"resourceReference\" data-resourceId=\"108235\" data-resourceType=\"BiblicaStudyNotesKeyTerms\">gracia</span> y viven en <span data-bnType=\"resourceReference\" data-resourceId=\"108211\" data-resourceType=\"BiblicaStudyNotesKeyTerms\">paz</span> con Dios. Están llenos de alegría y esperanza porque Dios compartirá su gloria con ellos. Pueden estar alegres incluso cuando enfrentan sufrimiento. Sus sufrimientos producen cosas buenas como fortaleza y carácter en sus vidas. Esto lleva a la esperanza. El amor de Dios es lo que la gente realmente necesita y espera. Dios da su amor libremente. El Espíritu Santo llena el corazón de las personas con el amor de Dios. La muerte de Jesús en la <span data-bnType=\"resourceReference\" data-resourceId=\"108530\" data-resourceType=\"BiblicaStudyNotesKeyTerms\">cruz</span> mostró cuán profundo es el amor de Dios por las personas. Jesús dio su vida por las personas. Lo hizo hasta por <span data-bnType=\"resourceReference\" data-resourceId=\"108525\" data-resourceType=\"BiblicaStudyNotesKeyTerms\">personas impías</span>. Lo hizo mientras estaban comprometidos con el pecado y oponiéndose a Dios. Como resultado, los creyentes pueden confiar en que serán salvados en el <span data-bnType=\"resourceReference\" data-resourceId=\"108055\" data-resourceType=\"BiblicaStudyNotesKeyTerms\">día del juicio</span>. Serán salvados de la ira de Dios contra el pecado y el mal.</p>",
    "associations": {
      "passage": [
        {
          "start_ref": "45005001",
          "start_ref_usfm": "ROM 5:1",
          "end_ref": "45005011",
          "end_ref_usfm": "ROM 5:11"
        }
      ],
      "resource": [
        {
          "reference_id": 108055,
          "content_id": 232024,
          "resource_code": "BiblicaStudyNotesKeyTerms",
          "label": "Día del juicio",
          "language": "spa"
        },
        {
          "reference_id": 108211,
          "content_id": 232180,
          "resource_code": "BiblicaStudyNotesKeyTerms",
          "label": "Paz",
          "language": "spa"
        },
        {
          "reference_id": 108235,
          "content_id": 232204,
          "resource_code": "BiblicaStudyNotesKeyTerms",
          "label": "Gracia",
          "language": "spa"
        },
        {
          "reference_id": 108525,
          "content_id": 232494,
          "resource_code": "BiblicaStudyNotesKeyTerms",
          "label": "Personas impías",
          "language": "spa"
        },
        {
          "reference_id": 108530,
          "content_id": 232499,
          "resource_code": "BiblicaStudyNotesKeyTerms",
          "label": "Cruz",
          "language": "spa"
        }
      ]
    }
  },
  {
    "content_id": 296635,
    "reference_id": 108890,
    "title": "Romanos 5:12–21",
    "media_type": "Text",
    "index_reference": "45005012-45005021",
    "language": "spa",
    "content": "<p><span data-bnType=\"resourceReference\" data-resourceId=\"108203\" data-resourceType=\"BiblicaStudyNotesKeyTerms\">Adán</span> fue el primer ser humano y fue el modelo para todas las personas. Adán pecó. Esto trajo la muerte al mundo. El pecado y la muerte gobiernan sobre mundo de Dios y sobre las personas. Los seres humanos pecan y los seres humanos mueren. Jesús es el primer ser humano en ser completamente fiel a Dios. Él no pecó. Estaba dispuesto a morir por amor a las personas. Dios lo resucitó de entre los muertos. Esto trajo vida que la muerte no puede destruir y detuvo a la muerte de gobernar sobre el mundo. Adán fue el primer modelo de cómo viven las personas. Jesús es el nuevo y último modelo. Esto significa que él mostró a las personas cómo vivir para Dios. Aquellos que confían en Jesús reciben el don de la gracia de Dios. La gracia de Dios es mayor y más fuerte que todo el daño que trae el pecado. Las personas que son justificadas con Dios son gobernadas por la gracia y no por el pecado. Ellos gobernarán con Jesús en el <span data-bnType=\"resourceReference\" data-resourceId=\"108561\" data-resourceType=\"BiblicaStudyNotesKeyTerms\">reino de Dios</span>.</p>",
    "associations": {
      "passage": [
        {
          "start_ref": "45005012",
          "start_ref_usfm": "ROM 5:12",
          "end_ref": "45005021",
          "end_ref_usfm": "ROM 5:21"
        }
      ],
      "resource": [
        {
          "reference_id": 108203,
          "content_id": 232172,
          "resource_code": "BiblicaStudyNotesKeyTerms",
          "label": "Adán",
          "language": "spa"
        },
        {
          "reference_id": 108561,
          "content_id": 232530,
          "resource_code": "BiblicaStudyNotesKeyTerms",
          "label": "Reino de Dios",
          "language": "spa"
        }
      ]
    }
  },
  {
    "content_id": 296636,
    "reference_id": 108891,
    "title": "Romanos 6:1–23",
    "media_type": "Text",
    "index_reference": "45006001-45006023",
    "language": "spa",
    "content": "<p>Las personas no debería usar la gracia de Dios como excusa para seguir pecando. Jesús salva a las personas de la esclavitud del pecado y la muerte. Como señal de que están salvados, los creyentes son <span data-bnType=\"resourceReference\" data-resourceId=\"108037\" data-resourceType=\"BiblicaStudyNotesKeyTerms\">bautizados</span>. Sumergirse en el agua es como morir y ser enterrado con Jesús. Salir del agua es como resucitar con Cristo de entre los muertos. Los creyentes son resucitados para vivir una nueva vida. La nueva libertad que los creyentes disfrutan se basa en hacer morir quien solían ser antes. Solían ser gobernados por el pecado. Pero todos sus antiguos caminos son muertos en la cruz con Cristo. Han cambiado y el pecado ya no los gobierna. Ahora están bajo el gobierno de Dios. Pablo describió esto como ser esclavo de Dios en lugar de serlo del pecado. Los seguidores de Dios desean servirle. Usan su libertad para seguir a Jesús su Señor. Ya no quieren servir al pecado y la muerte. Sirviendo a Cristo, sus seguidores reciben la bendición de una <span data-bnType=\"resourceReference\" data-resourceId=\"108044\" data-resourceType=\"BiblicaStudyNotesKeyTerms\">vida santa</span>.</p>",
    "associations": {
      "passage": [
        {
          "start_ref": "45006001",
          "start_ref_usfm": "ROM 6:1",
          "end_ref": "45006023",
          "end_ref_usfm": "ROM 6:23"
        }
      ],
      "resource": [
        {
          "reference_id": 108037,
          "content_id": 232006,
          "resource_code": "BiblicaStudyNotesKeyTerms",
          "label": "Bautismo",
          "language": "spa"
        },
        {
          "reference_id": 108044,
          "content_id": 232013,
          "resource_code": "BiblicaStudyNotesKeyTerms",
          "label": "Vida santa",
          "language": "spa"
        }
      ]
    }
  },
  {
    "content_id": 296637,
    "reference_id": 108892,
    "title": "Romanos 7:1–25",
    "media_type": "Text",
    "index_reference": "45007001-45007025",
    "language": "spa",
    "content": "<p>Cuando Jesús murió, fue como si sus seguidores también hubieran muerto. Sus cuerpos no habían muerto, pero habían muerto al pecado. Una vez que las personas están muertas al pecado, significa que el pecado ya no las controla. Pertenecen a Jesús y viven para Dios. En esta parte de la carta, Pablo parecía hablar mucho sobre sí mismo. Usó la palabra &quot;yo&quot; muchas veces. No solo estaba hablando de sí mismo. También estaba hablando de la historia de Israel con la Ley de Moisés. Al pueblo de Israel se le había dado la ley. La ley le mostró a las personas que están atrapadas como esclavas del pecado. La ley es buena y verdadera. Es un regalo de Dios. Pero no tiene el poder para producir el bien que Dios quiere que las personas hagan. Las personas deben ser cambiadas completamente para que esto suceda. Las personas son cambiadas completamente cuando Jesucristo las salva. El Espíritu Santo le da al pueblo de Dios el poder para decir no al pecado.</p>",
    "associations": {
      "passage": [
        {
          "start_ref": "45007001",
          "start_ref_usfm": "ROM 7:1",
          "end_ref": "45007025",
          "end_ref_usfm": "ROM 7:25"
        }
      ],
      "resource": []
    }
  },
  {
    "content_id": 296638,
    "reference_id": 108893,
    "title": "Romanos 8:1–17",
    "media_type": "Text",
    "index_reference": "45008001-45008017",
    "language": "spa",
    "content": "<p>Pablo describió dos tipos de leyes. Una era la ley del pecado. Estaba hablando de cómo el pecado controla a las personas. Cuando las personas pecan, son culpables de desobedecer a Dios. Son juzgadas por esto. El juicio es que todos los seres humanos mueren. El otro tipo de ley que Pablo describió era la ley del Espíritu Santo. Estaba hablando de cómo las personas que pertenecen a Cristo están libres del poder del pecado. El <span data-bnType=\"resourceReference\" data-resourceId=\"108526\" data-resourceType=\"BiblicaStudyNotesKeyTerms\">Hijo de Dios</span> vino a la tierra como un ser humano. Debido a esto, pudo convertirse en una <span data-bnType=\"resourceReference\" data-resourceId=\"108353\" data-resourceType=\"BiblicaStudyNotesKeyTerms\">ofrenda de pecado</span>. El sacrificio de Jesús pagó el precio del pecado. Esto significa que Jesús rompió el poder del pecado sobre los seres humanos. Los creyentes ya no son juzgados como culpables por elegir no obedecer a Dios. El Espíritu Santo les ayuda a pensar y vivir de maneras que agradan a Dios. Tendrán vida incluso después de que sus cuerpos mueran porque el Espíritu de Dios está en ellos. Aquellos que viven bajo el poder del Espíritu son parte de la <span data-bnType=\"resourceReference\" data-resourceId=\"108045\" data-resourceType=\"BiblicaStudyNotesKeyTerms\">familia de Dios</span>. Han sido <span data-bnType=\"resourceReference\" data-resourceId=\"108140\" data-resourceType=\"BiblicaStudyNotesKeyTerms\">adoptados</span> como hijos de Dios. Confían en Dios como su <span data-bnType=\"resourceReference\" data-resourceId=\"108312\" data-resourceType=\"BiblicaStudyNotesKeyTerms\">Padre</span> y lo llaman <span data-bnType=\"resourceReference\" data-resourceId=\"108141\" data-resourceType=\"BiblicaStudyNotesKeyTerms\">Abba</span>. El Espíritu Santo les da el poder para vivir para Dios. Les da el poder para seguir adelante cuando son <span data-bnType=\"resourceReference\" data-resourceId=\"108054\" data-resourceType=\"BiblicaStudyNotesKeyTerms\">maltratados</span> por seguir a Jesús. Un día, Jesús compartirá su gloria con todos los creyentes.</p>",
    "associations": {
      "passage": [
        {
          "start_ref": "45008001",
          "start_ref_usfm": "ROM 8:1",
          "end_ref": "45008017",
          "end_ref_usfm": "ROM 8:17"
        }
      ],
      "resource": [
        {
          "reference_id": 108045,
          "content_id": 232014,
          "resource_code": "BiblicaStudyNotesKeyTerms",
          "label": "La familia de Dios",
          "language": "spa"
        },
        {
          "reference_id": 108054,
          "content_id": 232023,
          "resource_code": "BiblicaStudyNotesKeyTerms",
          "label": "Maltratado",
          "language": "spa"
        },
        {
          "reference_id": 108140,
          "content_id": 232109,
          "resource_code": "BiblicaStudyNotesKeyTerms",
          "label": "Adoptado",
          "language": "spa"
        },
        {
          "reference_id": 108141,
          "content_id": 232110,
          "resource_code": "BiblicaStudyNotesKeyTerms",
          "label": "Abba",
          "language": "spa"
        },
        {
          "reference_id": 108312,
          "content_id": 232281,
          "resource_code": "BiblicaStudyNotesKeyTerms",
          "label": "Padre",
          "language": "spa"
        },
        {
          "reference_id": 108353,
          "content_id": 232322,
          "resource_code": "BiblicaStudyNotesKeyTerms",
          "label": "Ofrendas por el pecado",
          "language": "spa"
        },
        {
          "reference_id": 108526,
          "content_id": 232495,
          "resource_code": "BiblicaStudyNotesKeyTerms",
          "label": "Hijo de Dios",
          "language": "spa"
        }
      ]
    }
  },
  {
    "content_id": 296639,
    "reference_id": 108894,
    "title": "Romanos 8:18–25",
    "media_type": "Text",
    "index_reference": "45008018-45008025",
    "language": "spa",
    "content": "<p>Pablo explicó la futura gloria que vendrá. El mundo volverá a ser de la manera en Dios lo creó para ser. Los cuerpos de los creyentes que han muerto serán resucitados para vivir para siempre. Todo lo que Dios creó será liberado de la muerte y el sufrimiento. Todo el mundo sufre a causa del mal. Pablo describió esto como dolor y sufrimiento. Los creyentes y el resto de la creación anhelan la futura gloria que Dios ha prometido.</p>",
    "associations": {
      "passage": [
        {
          "start_ref": "45008018",
          "start_ref_usfm": "ROM 8:18",
          "end_ref": "45008025",
          "end_ref_usfm": "ROM 8:25"
        }
      ],
      "resource": []
    }
  },
  {
    "content_id": 296640,
    "reference_id": 108895,
    "title": "Romanos 8:26–39",
    "media_type": "Text",
    "index_reference": "45008026-45008039",
    "language": "spa",
    "content": "<p>Dios el Padre, Jesús el Hijo y el Espíritu Santo trabajan juntos para salvar a las personas. El Espíritu Santo ruega por los creyentes. Las <span data-bnType=\"resourceReference\" data-resourceId=\"108227\" data-resourceType=\"BiblicaStudyNotesKeyTerms\">oraciones</span> del Espíritu van mucho más allá de lo que se puede decir con palabras humanas. El Espíritu sabe lo que Dios quiere para sus hijos. Jesús también ora por los creyentes. Él comparte su gloria con todos sus hermanos y hermanas. Dios quiere que las personas sepan cuán profundamente él las ama. Nada puede hacer que Dios deje de amar a las personas. Las personas pueden estar completamente seguras de esto. Dios ha eliminado todos los cargos contra los creyentes por ser culpables de pecado. Así que el pecado no puede impedir que sean amados por Dios. Tampoco pueden hacerlo los <span data-bnType=\"resourceReference\" data-resourceId=\"108423\" data-resourceType=\"BiblicaStudyNotesKeyTerms\">seres espirituales</span> como los <span data-bnType=\"resourceReference\" data-resourceId=\"108313\" data-resourceType=\"BiblicaStudyNotesKeyTerms\">ángeles</span> o los <span data-bnType=\"resourceReference\" data-resourceId=\"108218\" data-resourceType=\"BiblicaStudyNotesKeyTerms\">seres espirituales malignos</span> como los demonios. Ni siquiera la muerte puede impedir que el amor de Dios llegue a las personas. Esto es porque Jesús ganó la victoria sobre la muerte. No hay límites para la victoria de Jesús el Mesías. Muchas cosas intentan detener el propósito de Dios para las vidas de los creyentes. Pero debido a la victoria de Jesús, los creyentes pueden ganar la victoria sobre todas esas cosas. El propósito de Dios es salvar a las personas para que puedan ser como Jesús.</p>",
    "associations": {
      "passage": [
        {
          "start_ref": "45008026",
          "start_ref_usfm": "ROM 8:26",
          "end_ref": "45008039",
          "end_ref_usfm": "ROM 8:39"
        }
      ],
      "resource": [
        {
          "reference_id": 108218,
          "content_id": 232187,
          "resource_code": "BiblicaStudyNotesKeyTerms",
          "label": "Seres espirituales malignos",
          "language": "spa"
        },
        {
          "reference_id": 108227,
          "content_id": 232196,
          "resource_code": "BiblicaStudyNotesKeyTerms",
          "label": "Oración",
          "language": "spa"
        },
        {
          "reference_id": 108313,
          "content_id": 232282,
          "resource_code": "BiblicaStudyNotesKeyTerms",
          "label": "Ángel",
          "language": "spa"
        },
        {
          "reference_id": 108423,
          "content_id": 232392,
          "resource_code": "BiblicaStudyNotesKeyTerms",
          "label": "Seres espirituales",
          "language": "spa"
        }
      ]
    }
  },
  {
    "content_id": 296641,
    "reference_id": 108896,
    "title": "Romanos 9:1–18",
    "media_type": "Text",
    "index_reference": "45009001-45009018",
    "language": "spa",
    "content": "<p>Pablo era parte del pueblo de Israel. Ellos se negaron a aceptar que Jesús es el Mesías enviado por Dios. Pablo estaba profundamente triste por esto. Habría renunciado al amor de Jesús por él para ayudar a Israel a aceptar a Jesús. Pero eso no habría ayudado. Dios le dio a Israel muchos dones como el <span data-bnType=\"resourceReference\" data-resourceId=\"108417\" data-resourceType=\"BiblicaStudyNotesKeyTerms\">templo</span>, la ley y sus promesas. Sin embargo, muchas personas en Israel no creían que Jesús es el Mesías. Esto no significaba que la palabra de Dios y sus alianzas hubieran fallado. Dios es fiel y lo que dice es verdad. Dios había elegido trabajar a través de Abraham en su plan para salvar al mundo. Dios quería que la línea familiar de Abraham recibiera su misericordia y amor. Dios continuó su plan a través del hijo de Abraham, <span data-bnType=\"resourceReference\" data-resourceId=\"108261\" data-resourceType=\"BiblicaStudyNotesKeyTerms\">Isaac</span>, y el hijo de Isaac, Jacob. Pero ser parte de la línea familiar de Jacob no es lo que hace a alguien hijo de Dios. Todos los que aceptan la misericordia y el amor de Dios son hijos de Dios.</p>",
    "associations": {
      "passage": [
        {
          "start_ref": "45009001",
          "start_ref_usfm": "ROM 9:1",
          "end_ref": "45009018",
          "end_ref_usfm": "ROM 9:18"
        }
      ],
      "resource": [
        {
          "reference_id": 108261,
          "content_id": 232230,
          "resource_code": "BiblicaStudyNotesKeyTerms",
          "label": "Isaac",
          "language": "spa"
        },
        {
          "reference_id": 108417,
          "content_id": 232386,
          "resource_code": "BiblicaStudyNotesKeyTerms",
          "label": "Templo",
          "language": "spa"
        }
      ]
    }
  },
  {
    "content_id": 296642,
    "reference_id": 108897,
    "title": "Romanos 9:19–33",
    "media_type": "Text",
    "index_reference": "45009019-45009033",
    "language": "spa",
    "content": "<p>Pablo usó palabras de varios <span data-bnType=\"resourceReference\" data-resourceId=\"108416\" data-resourceType=\"BiblicaStudyNotesKeyTerms\">profetas</span> en el <span data-bnType=\"resourceReference\" data-resourceId=\"108192\" data-resourceType=\"BiblicaStudyNotesKeyTerms\">Antiguo Testamento</span>. Hizo esto para hablar sobre quiénes son el pueblo de Dios. <span data-bnType=\"resourceReference\" data-resourceId=\"108399\" data-resourceType=\"BiblicaStudyNotesKeyTerms\">Profecías</span> en el libro de <span data-bnType=\"resourceReference\" data-resourceId=\"108497\" data-resourceType=\"BiblicaStudyNotesKeyTerms\">Isaías</span> describieron a Dios como un alfarero. Describieron a Israel como el barro. Dios estaba tratando de formar y moldear la nación de Israel. Quería que fueran un <span data-bnType=\"resourceReference\" data-resourceId=\"108337\" data-resourceType=\"BiblicaStudyNotesKeyTerms\">reino de sacerdotes</span> y una nación <span data-bnType=\"resourceReference\" data-resourceId=\"108361\" data-resourceType=\"BiblicaStudyNotesKeyTerms\">santa</span>. Las profecías de Isaías y <span data-bnType=\"resourceReference\" data-resourceId=\"108570\" data-resourceType=\"BiblicaStudyNotesKeyTerms\">Oseas</span> mostraron que el pueblo de Dios incluiría tanto a judíos como a gentiles. El pueblo de Dios no es elegido porque conocen la ley. No son elegidos según por la familia que provienen. Son elegidos porque ponen su confianza en Jesús. Esto demuestra que tienen fe en Dios. No están tratando de justificarse ante Dios. Confían en Jesús para que los justifique ante Dios.</p>",
    "associations": {
      "passage": [
        {
          "start_ref": "45009019",
          "start_ref_usfm": "ROM 9:19",
          "end_ref": "45009033",
          "end_ref_usfm": "ROM 9:33"
        }
      ],
      "resource": [
        {
          "reference_id": 108192,
          "content_id": 232161,
          "resource_code": "BiblicaStudyNotesKeyTerms",
          "label": "Antiguo Testamento",
          "language": "spa"
        },
        {
          "reference_id": 108337,
          "content_id": 232306,
          "resource_code": "BiblicaStudyNotesKeyTerms",
          "label": "Reino de sacerdotes",
          "language": "spa"
        },
        {
          "reference_id": 108361,
          "content_id": 232330,
          "resource_code": "BiblicaStudyNotesKeyTerms",
          "label": "Santo",
          "language": "spa"
        },
        {
          "reference_id": 108399,
          "content_id": 232368,
          "resource_code": "BiblicaStudyNotesKeyTerms",
          "label": "Profecía",
          "language": "spa"
        },
        {
          "reference_id": 108416,
          "content_id": 232385,
          "resource_code": "BiblicaStudyNotesKeyTerms",
          "label": "Profeta",
          "language": "spa"
        },
        {
          "reference_id": 108497,
          "content_id": 232466,
          "resource_code": "BiblicaStudyNotesKeyTerms",
          "label": "Isaías",
          "language": "spa"
        },
        {
          "reference_id": 108570,
          "content_id": 232539,
          "resource_code": "BiblicaStudyNotesKeyTerms",
          "label": "Oseas",
          "language": "spa"
        }
      ]
    }
  },
  {
    "content_id": 296643,
    "reference_id": 108898,
    "title": "Romanos 10:1–21",
    "media_type": "Text",
    "index_reference": "45010001-45010021",
    "language": "spa",
    "content": "<p>Pablo explicó que muchos judíos realmente querían obedecer a Dios. Intentaron hacerlo obedeciendo la Ley de Moisés. Pensaban que tenían el poder de obedecer la ley perfectamente. Creían que esto les traería paz con Dios. No entendían que los humanos no tienen el poder de hacerse justos ante Dios. Solo Dios tiene este poder. Dios justifica a las personas con él cuando tienen fe en él. Las personas solo pueden creer en Jesús si han oído hablar de él. Pablo usó palabras del Salmo 19 para mostrar algo sobre la creación. El sol, la luna y las estrellas son testigos para todos en la tierra sobre quién es Dios. Pablo dejó claro que los judíos habían escuchado el mensaje sobre Jesús.</p>",
    "associations": {
      "passage": [
        {
          "start_ref": "45010001",
          "start_ref_usfm": "ROM 10:1",
          "end_ref": "45010021",
          "end_ref_usfm": "ROM 10:21"
        }
      ],
      "resource": []
    }
  },
  {
    "content_id": 296644,
    "reference_id": 108899,
    "title": "Romanos 11:1–24",
    "media_type": "Text",
    "index_reference": "45011001-45011024",
    "language": "spa",
    "content": "<p>Pablo mostró que no todos en Israel habían fallado en aceptar al Mesías. Pablo y muchos otros judíos habían recibido la gracia de Dios y habían creído en Jesús. Otros judíos no creyeron. Esto se debió a que eran tercos y eligieron no hacerlo. Esto le permitió a los gentiles la oportunidad de escuchar acerca de Jesús y volverse a Dios. Pablo quería seguir compartiendo el mensaje sobre Jesús con otras naciones y pueblos. Cuando los gentiles recibieron la bendición de conocer a Dios, muchos judíos se pusieron celosos. Pablo quería que todo Israel se pusiera celoso de aquellos que conocían a Dios. Esperaba que esto animara a los judíos a aceptar a Jesús. Pablo describió a judíos y gentiles como <span data-bnType=\"resourceReference\" data-resourceId=\"108142\" data-resourceType=\"BiblicaStudyNotesKeyTerms\">olivos</span>. La nación de Israel era como un olivo en un bonito jardín. Los creyentes gentiles eran como un olivo que crecía en la naturaleza. Las ramas de este olivo silvestre se unieron al olivo judío. La raíz judía sostenía todas las ramas silvestres que se unieron a él. Esa es una imagen de cómo los gentiles se unen a la familia de Dios. Dios es quien une las ramas gentiles al árbol judío. Algunas ramas del olivo judío habían sido cortadas. Esos eran los judíos que se negaron a aceptar lo que Dios estaba haciendo a través de Jesús. Pablo esperaba que todos los judíos creyeran que Jesús es el Mesías. Entonces Dios volvería a poner todas las ramas judías en el olivo nuevamente. Pablo anhelaba que eso sucediera.</p>",
    "associations": {
      "passage": [
        {
          "start_ref": "45011001",
          "start_ref_usfm": "ROM 11:1",
          "end_ref": "45011024",
          "end_ref_usfm": "ROM 11:24"
        }
      ],
      "resource": [
        {
          "reference_id": 108142,
          "content_id": 232111,
          "resource_code": "BiblicaStudyNotesKeyTerms",
          "label": "Olivo",
          "language": "spa"
        }
      ]
    }
  },
  {
    "content_id": 296645,
    "reference_id": 108900,
    "title": "Romanos 11:25–36",
    "media_type": "Text",
    "index_reference": "45011025-45011036",
    "language": "spa",
    "content": "<p>Cuando los judíos se negaron a aceptar las buenas nuevas sobre Jesús, el mensaje fue compartido con los gentiles. Esto no significaba que Dios dejó de preocuparse por los judíos. El amor de Dios por su pueblo Israel dura para siempre. Tanto judíos como gentiles son culpables de no obedecer a Dios. Sin embargo, Dios está lleno de misericordia. Él es fiel a su promesa de liberar a las personas del poder del pecado. La misericordia de Dios llenó a Pablo de asombro. Pablo escribió su alabanza a Dios como un <span data-bnType=\"resourceReference\" data-resourceId=\"108204\" data-resourceType=\"BiblicaStudyNotesKeyTerms\">poema</span> o una canción. Nadie sabe lo que Dios hará antes de que lo haga. Dios obra de maneras sorprendentes. Su <span data-bnType=\"resourceReference\" data-resourceId=\"108325\" data-resourceType=\"BiblicaStudyNotesKeyTerms\">sabiduría</span> es maravillosa y mucho mayor de lo que los humanos pueden entender. La vida de todas las cosas en la tierra depende de Dios. Así que toda la gloria y el honor son suyos ahora y para siempre.</p>",
    "associations": {
      "passage": [
        {
          "start_ref": "45011025",
          "start_ref_usfm": "ROM 11:25",
          "end_ref": "45011036",
          "end_ref_usfm": "ROM 11:36"
        }
      ],
      "resource": [
        {
          "reference_id": 108204,
          "content_id": 232173,
          "resource_code": "BiblicaStudyNotesKeyTerms",
          "label": "Poema",
          "language": "spa"
        },
        {
          "reference_id": 108325,
          "content_id": 232294,
          "resource_code": "BiblicaStudyNotesKeyTerms",
          "label": "Sabiduría",
          "language": "spa"
        }
      ]
    }
  },
  {
    "content_id": 296646,
    "reference_id": 108901,
    "title": "Romanos 12:1–21",
    "media_type": "Text",
    "index_reference": "45012001-45012021",
    "language": "spa",
    "content": "<p>Los creyentes estaban agradecidos por la misericordia de Dios. Lo demostraron sirviendo a Dios con sus mentes y sus cuerpos. Dejaron de pensar y actuar de la manera que Pablo llamaba de la forma mundana de vivir. Él estaba hablando de ser controlado por deseos pecaminosos. El amor de Dios cambia completamente la forma en que los creyentes piensan y actúan. Sirven a Dios juntos como hermanos y hermanas. El pueblo de Dios es todo diferente entre sí. Pero todos confían en Jesús. De esta manera se hacen uno. Pablo describió esto como un cuerpo que tiene muchas partes diferentes. Aunque las partes hacen cosas diferentes, pertenecen al mismo cuerpo. Los seguidores de Jesús tienen muchos dones diferentes. Debido a esto, hacen diferentes tipos de trabajo. Pero se unen como uno en el <span data-bnType=\"resourceReference\" data-resourceId=\"108143\" data-resourceType=\"BiblicaStudyNotesKeyTerms\">cuerpo de Cristo</span>. Vivir juntos como el cuerpo de Cristo significa vivir en paz. Esto incluye ser humilde y honesto. Los creyentes están llenos de esperanza, alegría, paciencia y fe. Ellos se aseguran de que otras personas tengan lo que necesitan y comparten con los demás. Esto incluye compartir su alegría o tristeza. Los creyentes hacen el bien incluso a personas que quieren causan daño. Los creyentes confían en que Dios traerá juicio contra las personas que están haciendo el mal. Esto es porque solo el amor de Dios es lo suficientemente fuerte como para detener el poder del mal.</p>",
    "associations": {
      "passage": [
        {
          "start_ref": "45012001",
          "start_ref_usfm": "ROM 12:1",
          "end_ref": "45012021",
          "end_ref_usfm": "ROM 12:21"
        }
      ],
      "resource": [
        {
          "reference_id": 108143,
          "content_id": 232112,
          "resource_code": "BiblicaStudyNotesKeyTerms",
          "label": "Cuerpo de Cristo",
          "language": "spa"
        }
      ]
    }
  },
  {
    "content_id": 296647,
    "reference_id": 108902,
    "title": "Romanos 13:1–7",
    "media_type": "Text",
    "index_reference": "45013001-45013007",
    "language": "spa",
    "content": "<p>Pablo explicó que Dios designó gobiernos para asegurarse que haya orden y justicia. Así que los creyentes deben dar a las autoridades todo lo que necesitan para hacer bien su trabajo. Esto puede incluir respeto, honor e <span data-bnType=\"resourceReference\" data-resourceId=\"108577\" data-resourceType=\"BiblicaStudyNotesKeyTerms\">impuestos</span>. Pablo mostró cómo los gobiernos son responsables en servir a Dios y hacer lo correcto. Habló con firmeza sobre cómo Dios designa a los líderes y gobernantes para este trabajo. Ellos deben castigar a las personas por hacer lo incorrecto. Algunos gobernantes castigaban a las personas que no habían hecho nada malo. Esto le pasó a Jesús. Cuando los hijos de Dios tienen conflictos con las autoridades, deben elegir obedecer a Dios. Los capítulos 4 y 5 de Hechos cuentan una historia sobre esto.</p>",
    "associations": {
      "passage": [
        {
          "start_ref": "45013001",
          "start_ref_usfm": "ROM 13:1",
          "end_ref": "45013007",
          "end_ref_usfm": "ROM 13:7"
        }
      ],
      "resource": [
        {
          "reference_id": 108577,
          "content_id": 232546,
          "resource_code": "BiblicaStudyNotesKeyTerms",
          "label": "Impuestos",
          "language": "spa"
        }
      ]
    }
  },
  {
    "content_id": 296648,
    "reference_id": 108903,
    "title": "Romanos 13:8–14",
    "media_type": "Text",
    "index_reference": "45013008-45013014",
    "language": "spa",
    "content": "<p>La Ley de Moisés le mostró a Israel cómo vivir. La forma de vivir que Jesús enseñó a sus seguidores es como una nueva ley. La ley o mandamiento de Jesús era que las personas se amaran unas a otras (Juan 15:12). Cuando las personas aman a los demás, están haciendo todo lo que la Ley de Moisés requería. Los creyentes debían mostrar amor por los demás mientras esperan el <span data-bnType=\"resourceReference\" data-resourceId=\"108065\" data-resourceType=\"BiblicaStudyNotesKeyTerms\">regreso de Jesús</span> a la tierra. Pablo comparó este tiempo de espera como despertarse por la mañana después de dormir. La noche era cuando las personas hacían cosas malas antes de comenzar a seguir a Jesús. El día es cuando Jesús regresa a la tierra y las personas lo obedecen completamente. Pablo quería que los creyentes comenzaran a vivir ahora de la manera en que vivirán cuando Jesús regrese. Pablo describió esto como ponerse a Jesús como si fuera ropa que llevan puesta. Esto significa que los creyentes deben estar cerca de Jesús como la ropa está cerca de su piel. También significa que otros pueden ver que los creyentes están siguiendo a Jesús fielmente.</p>",
    "associations": {
      "passage": [
        {
          "start_ref": "45013008",
          "start_ref_usfm": "ROM 13:8",
          "end_ref": "45013014",
          "end_ref_usfm": "ROM 13:14"
        }
      ],
      "resource": [
        {
          "reference_id": 108065,
          "content_id": 232034,
          "resource_code": "BiblicaStudyNotesKeyTerms",
          "label": "El regreso de Jesús",
          "language": "spa"
        }
      ]
    }
  },
  {
    "content_id": 296649,
    "reference_id": 108904,
    "title": "Romanos 14:1–23",
    "media_type": "Text",
    "index_reference": "45014001-45014023",
    "language": "spa",
    "content": "<p>Pablo le recordó a los creyentes en Roma que las personas a menudo tienen diferentes opiniones acerca de cosas. Esto era cierto en su comprensión sobre alimentos, bebidas y días sagrados. Pablo les dio instrucciones sobre cómo vivir en paz con personas que tienen opiniones diferentes. No deben discutir sobre sus diferencias. No deben tratar de parecer más importantes que los demás. Deben proteger a la fe de los demás y alentarla a crecer más fuerte. Deben vivir en paz, ser agradecidos y alegres. Lo más importante es que los creyentes continúen sirviendo y amando a los demás como lo hizo Jesús. Los creyentes sirven a Dios como su Señor y Maestro. Dios es el juez de todas las personas. Así que los creyentes no deben intentar juzgar cuán fieles son los demás a Dios.</p>",
    "associations": {
      "passage": [
        {
          "start_ref": "45014001",
          "start_ref_usfm": "ROM 14:1",
          "end_ref": "45014023",
          "end_ref_usfm": "ROM 14:23"
        }
      ],
      "resource": []
    }
  },
  {
    "content_id": 296650,
    "reference_id": 108905,
    "title": "Romanos 15:1–16",
    "media_type": "Text",
    "index_reference": "45015001-45015016",
    "language": "spa",
    "content": "<p>Pablo continuó dando instrucciones sobre cómo los creyentes pueden vivir en paz unos con otros. Deben tratarse entre sí de la misma manera en la que Jesús trató a las personas cuando estuvo en la tierra. Jesús no hizo solamente lo que era bueno para él mismo. En cambio, hizo lo que era bueno para otras personas. Aceptó a los demás y fue un siervo. Cuando Jesús sirvió a las personas, esto les dio la oportunidad de aprender sobre Dios. Jesús mostró que Dios es real y se puede confiar completamente en él. Dios es un Dios de esperanza. Está lleno de misericordia y quiere que su pueblo sea fuerte en su fe. Pablo oró para que el pueblo de Dios estuviera lleno de gozo y paz. El Espíritu Santo llena al pueblo de Dios con esperanza. También encuentran gozo y esperanza cuando leen las Escrituras. Pablo mostró cómo las promesas que Dios hizo a Israel incluían bendiciones para todas las naciones. La misericordia, el gozo, la esperanza y la paz de Dios son para todas las personas que confían en él. Los creyentes pueden ser muy diferentes unos de otros. Sin embargo, dar gloria a Dios los une como uno.</p>",
    "associations": {
      "passage": [
        {
          "start_ref": "45015001",
          "start_ref_usfm": "ROM 15:1",
          "end_ref": "45015016",
          "end_ref_usfm": "ROM 15:16"
        }
      ],
      "resource": []
    }
  },
  {
    "content_id": 296651,
    "reference_id": 108906,
    "title": "Romanos 15:17–33",
    "media_type": "Text",
    "index_reference": "45015017-45015033",
    "language": "spa",
    "content": "<p>Cerca del final de su carta, Pablo escribió sobre el trabajo que había estado haciendo. Estaba agradecido por lo que Cristo había hecho a través de él. El Espíritu de Dios era lo que le daba la fuerza para hacer su trabajo. Su trabajo era compartir las buenas nuevas sobre Jesús. Las compartió con personas que nunca las habían escuchado antes. Hizo esto en las tierras controladas por el gobierno romano alrededor de <span data-bnType=\"resourceReference\" data-resourceId=\"108464\" data-resourceType=\"BiblicaStudyNotesKeyTerms\">Jerusalén</span>. Ahora quería predicar en <span data-bnType=\"resourceReference\" data-resourceId=\"108144\" data-resourceType=\"BiblicaStudyNotesKeyTerms\">España</span>. Su plan era visitar a los creyentes en Roma de camino a España. Estaba deseando ver cómo podían animarse mutuamente. Pero primero necesitaba ir a Jerusalén. Llevaba una ofrenda de dinero de los creyentes gentiles a los creyentes judíos necesitados allí. Los capítulos 21 al 28 de Hechos cuentan lo que sucedió. Pablo fue arrestado en Jerusalén. No pudo hacer el viaje a Roma y a España como había planeado. Sin embargo, unos años después fue enviado a Roma como prisionero. Fue entonces cuando conoció a los creyentes en Roma.</p>",
    "associations": {
      "passage": [
        {
          "start_ref": "45015017",
          "start_ref_usfm": "ROM 15:17",
          "end_ref": "45015033",
          "end_ref_usfm": "ROM 15:33"
        }
      ],
      "resource": [
        {
          "reference_id": 108144,
          "content_id": 232113,
          "resource_code": "BiblicaStudyNotesKeyTerms",
          "label": "España",
          "language": "spa"
        },
        {
          "reference_id": 108464,
          "content_id": 232433,
          "resource_code": "BiblicaStudyNotesKeyTerms",
          "label": "Jerusalén",
          "language": "spa"
        }
      ]
    }
  },
  {
    "content_id": 296652,
    "reference_id": 108907,
    "title": "Romanos 16:1–15",
    "media_type": "Text",
    "index_reference": "45016001-45016015",
    "language": "spa",
    "content": "<p>Pablo mencionó los nombres de muchos amigos y personas que trabajaron con él. Muchos de estos nombres también se encuentran en el libro de los Hechos y en <span data-bnType=\"resourceReference\" data-resourceId=\"108120\" data-resourceType=\"BiblicaStudyNotesKeyTerms\">las cartas de Pablo</span>. Esta lista da una imagen de cómo se difundió el mensaje sobre Jesús. Entre los mencionados en la lista figuran maestros, apóstoles y personas que recibieron a otros en su hogar. La lista menciona mujeres y hombres, judíos y gentiles. Incluye hermanos, hermanas, madres y familias enteras. Sufrieron juntos y algunos algunos estuvieron juntos en en la cárcel. Muchas personas diferentes trabajaron juntas como <span>compañeros</span> y amigos para compartir las buenas nuevas. Este grupo de personas muy diferentes sirvió al mundo como el cuerpo de Cristo.</p>",
    "associations": {
      "passage": [
        {
          "start_ref": "45016001",
          "start_ref_usfm": "ROM 16:1",
          "end_ref": "45016015",
          "end_ref_usfm": "ROM 16:15"
        }
      ],
      "resource": [
        {
          "reference_id": 108120,
          "content_id": 232089,
          "resource_code": "BiblicaStudyNotesKeyTerms",
          "label": "Las cartas de Pablo",
          "language": "spa"
        }
      ]
    }
  },
  {
    "content_id": 296653,
    "reference_id": 108908,
    "title": "Romanos 16:16–27",
    "media_type": "Text",
    "index_reference": "45016016-45016027",
    "language": "spa",
    "content": "<p>Las palabras finales de Pablo incluyeron saludos de algunos de sus ayudantes a los creyentes en Roma. También animó a los creyentes a mantenerse alejados de las personas que causaban problemas intencionalmente. Estas personas querían impedir que los creyentes vivieran juntos en paz. Debían mantenerse alejados de cualquier enseñanza que fuera en contra del mensaje sobre Jesús. Pablo llamó al mensaje sobre Jesús un misterio. En otras cartas, Pablo lo llamó el <span data-bnType=\"resourceReference\" data-resourceId=\"108145\" data-resourceType=\"BiblicaStudyNotesKeyTerms\">misterio de Cristo</span>. Este misterio había estado oculto pero ahora se había hecho claro. Dios hizo claro el misterio a través de las Escrituras de Israel. Había sido predicado por Pablo y otros que servían a Cristo fielmente. Dios quiere que todas las personas pongan su fe en él y le obedezcan. Cuando lo hacen, no tienen ninguna relación con el mal. En su lugar, están llenos de la paz y la gracia de Dios. Esto trae gloria a Dios.</p>",
    "associations": {
      "passage": [
        {
          "start_ref": "45016016",
          "start_ref_usfm": "ROM 16:16",
          "end_ref": "45016027",
          "end_ref_usfm": "ROM 16:27"
        }
      ],
      "resource": [
        {
          "reference_id": 108145,
          "content_id": 232114,
          "resource_code": "BiblicaStudyNotesKeyTerms",
          "label": "Misterio de Cristo",
          "language": "spa"
        }
      ]
    }
  }
]